{"lastError":"","response":{"reportBase":{"caseNum":"105,監宣,134","caseType":"V","codeNum":"監宣","content":"臺灣新竹地方法院民事裁定　　　　　　105年度監宣字第134號\n聲　請　人　林雪鳳　\n　　　　　　何西誠　\n相對人即受\n監護宣告人　何坤鑑　\n關　係　人　何西洲　\n　　　　　　彭崇德　\n　　　　　　彭明聖　\n上列當事人間選定監護人事件，本院裁定如下：\n    主  文\n選定林雪鳳（女、民國00年0月00日生，身分證統一編號：Z000000000號）為受監護宣告之人之監護人。\n指定何西誠（男、民國00年0月00日生，身分證統一編號：Z000000000號）為會同開具財產清冊之人。\n本件程序費用由受監護宣告之人何坤鑑負擔。\n    理  由\n一、聲請意旨略以：相對人即受監護宣告人何坤鑑（下稱相對人\n    ）為聲請人林雪鳳之公公、聲請人何西誠之父親，聲請人2\n    人為夫妻，相對人前於民國98年4月24日經鈞院以98年度禁\n    字第23號裁定宣告為禁治產人，並依法由相對人之配偶彭銀\n    英任其監護人，惟原監護人彭銀英已於105年2月5日死亡，\n    茲因經家人一致同意推舉由聲請人林雪鳳擔任其監護人，以\n    利日後代為處理事務，爰聲請由聲請人林雪鳳擔任相對人之\n    監護人，並指定聲請人何西誠為會同開具財產清冊之人等語\n    。\n二、按「民法總則中華民國97年5 月2 日修正之條文施行前，已\n    為禁治產宣告者，視為已為監護宣告」「民法規定之禁治產\n    或禁治產人，自民法總則中華民國97年5 月2 日修正之條文\n    施行後，一律改稱為監護或受監護宣告之人。」民法總則施\n    行法第4 條第2 項、第4 條之1 定有明文。又「中華民國97\n    年5 月2 日修正之民法親屬編第四章條文施行前所設置之監\n    護人，於修正施行後，適用修正後之規定。」民法親屬編施\n    行法第14條之2亦有明文。本件相對人前經本院98年度禁字\n    第23號民事裁定宣告為禁治產人，相對人之配偶彭銀英依修\n    正前民法第1111條第1項第1款規定為法定監護人，業據本院\n    職權調閱前開98度禁字第23號宣告禁治產事件卷宗核閱屬實\n    ，並有戶籍謄本在卷可稽。又，97年5月2日修正之民法親屬\n    編條文，業於98年11月23日施行，依前揭規定，視為本件相\n    對人業經本院為監護宣告，其監護人之權利義務於修正後應\n    適用修正後規定。\n三、次按，監護人有下列情形之一，且受監護人無第1094條第1\n    項之監護人者，法院得依受監護人、第1094條第3 項聲請權\n    人之聲請或依職權，另行選定適當之監護人：一、死亡。二\n    、經法院許可辭任。三、有第1096條各款情形之一，民法第\n    1106條第1 項定有明文，而此一規定依同法第1113條規定，\n    準用於成年人之監護。聲請人2人為相對人之四子及媳婦，\n    而相對人之原監護人彭銀英已於105年2月5日死亡，有戶籍\n    謄本附卷可稽，是聲請人2人既係相對人之子、媳，自得依\n    首揭規定，聲請為相對人另行選定監護人。\n四、再按，法院為監護之宣告時，應依職權就配偶、四親等內之\n    親屬、最近1 年有同居事實之其他親屬、主管機關、社會福\n    利機構或其他適當之人選定1 人或數人為監護人，並同時指\n    定會同開具財產清冊之人，民法第1110條、第1111條第1 項\n    定有明文。茲聲請人2人業據提出親屬系統表、本院上開裁\n    定及戶籍謄本等件為證，聲請人2人並到庭陳明願分別出任\n    監護人及會同開具財產清冊之人之職，關係人何西洲、彭崇\n    德、彭明聖亦出具同意書同意本件之聲請及由聲請人2人分\n    別出任監護人及會同開具財產清冊之人之意，復據本院職權\n    調閱前開98度禁字第23號宣告禁治產事件卷宗核閱屬實，是\n    相對人即受監護宣告之人，其配偶已歿，其之現存子女即聲\n    請人夫婦2人及關係人何西洲、彭崇德、彭明聖均與相對人\n    同住，而聲請人2人為相對人其餘子女何西洲、彭崇德、彭\n    明聖所共同推舉之監護人及會同開具財產清冊之人人選之情\n    甚明，審酌上情，認應由聲請人林雪鳳擔任相對人之監護人\n    ，最能符合受監護宣告人之最佳利益，爰選定聲請人林雪鳳\n    為相對人之監護人。又，聲請人何西誠為相對人之四子，亦\n    為聲請人林雪鳳之夫婿，經其到庭表明願擔任相對人之會同\n    開具財產清冊之人，爰併指定聲請人何西誠為相對人之會同\n    開具財產清冊之人，以維護相對人之利益。\n據上論結，本件聲請為有理由，應依家事事件法第164 條第2 項\n規定，裁定如主文。\n中    華    民    國   105    年    7     月    13    日\n               家事法庭  法      官  <a href=\"https://www.pingluweb.com.tw/#!judgeDetail?id=50e3f66221129327c1d37117\" target=\"_blank\">林建鼎</a>\n如對本裁定抗告，須於裁定送達後10日之不變期間內，向本院提\n出抗告狀，並繳納抗告費新臺幣1,000元。\n以上正本係照原本作成。\n中    華    民    國   105    年    7     月    13    日\n                         書  記  官  徐佩鈴\n附錄法文：\n民法第1099條：\n監護開始時，監護人對於受監護人之財產，應依規定會同遺囑指\n定、當地直轄市、縣（市）政府指派或法院指定之人，於二個月\n內開具財產清冊，並陳報法院。\n前項期間，法院得依監護人之聲請，於必要時延長之。\n民法第1099條之1 ：\n於前條之財產清冊開具完成並陳報法院前，監護人對於受監護人\n之財產，僅得為管理上必要之行為。\n","courtCode":"SCD","fulltext":null,"gist":null,"identifier":"SCDV,105,監宣,134,20160713,1-0bbfd789-c8ec-44cb-8b9a-194344b1b021","issue":"改定監護人","jno":"134","jtype":"R","judgeDate":1468339200000,"jyear":105,"lastUpdate":1594576361124,"reportStatus":7,"source":"opendata","summary":null},"report":{"amount":0,"appellant":null,"appellantAgent":null,"appellantLawyer":null,"appellee":null,"appelleeAgent":null,"appelleeLawyer":null,"assignCounsel":null,"beJudgedPerson":null,"caseNum":["105,監宣,134"],"caseType":"V","chosenCounsel":null,"clerk":"徐佩鈴","codeNum":"監宣","courtCode":"SCD","defendant":null,"defendantAgent":null,"defendantLawyer":null,"flag":false,"identifier":"SCDV,105,監宣,134,20160713,1-0bbfd789-c8ec-44cb-8b9a-194344b1b021","inmate":null,"interlocutoryPetitioner":null,"jno":"134","jtype":"R","judge":null,"judgeDate":1468339200000,"jyear":105,"lastUpdate":1594576361119,"lawyerCustomers":null,"level":1,"lose":null,"main":"選定林雪鳳（女、民國00年0月00日生，身分證統一編號：Z000000000號）為受監護宣告之人之監護人。\n指定何西誠（男、民國00年0月00日生，身分證統一編號：Z000000000號）為會同開具財產清冊之人。\n本件程序費用由受監護宣告之人何坤鑑負擔。","money":0,"petitioner":["何西洲","彭明聖","林雪鳳","何西誠","彭崇德","相對人即受"],"petitionerAgent":null,"petitionerLawyer":null,"plaintiff":null,"plaintiffAgent":null,"plaintiffLawyer":null,"presideJudge":"林建鼎","previousCaseNum":null,"previousCourtCode":null,"previousJudgeDate":null,"privateProsecutor":null,"proportion":0.0,"prosecutor":null,"publicDefender":null,"publicJudge":null,"puisne":null,"respondent":null,"result":0,"sentence":null,"statute":["民法第1110條","民法第1111條第1項第1款","民法第1099條","民法第1111條第1項","民法第1099條之1","民法第1113條","民法第1106條第1項"],"tags":null,"type":"民事裁定","win":null},"statute":[{"items":[{"cnum":"第一千零九十九條","num":"第1099條","val":1099},{"cnum":"第一千零九十九條之一","num":"第1099條之1","val":1099},{"cnum":"第一千一百零六條第一項","num":"第1106條第1項","val":1106},{"cnum":"第一千一百十條","num":"第1110條","val":1110},{"cnum":"第一千一百十一條第一項第一款","num":"第1111條第1項第1款","val":1111},{"cnum":"第一千一百十一條第一項","num":"第1111條第1項","val":1111},{"cnum":"第一千一百十三條","num":"第1113條","val":1113}],"statute":"民法"}],"tags":null},"success":true}