{"lastError":"","response":{"reportBase":{"caseNum":"103,家親聲,29","caseType":"V","codeNum":"家親聲","content":"臺灣基隆地方法院民事裁定　　　　　 103年度家親聲字第29號\n聲　請　人　王秋川\n上列原告與被告朱氏萬間請求改定監護人事件，本院裁定如下：\n    主  文\n原告應於本裁定送達後二十日內，補正：(一)與被告結婚之證明\n文件（上載有被告之越南住居所及年籍資料）；(二)被告之入出\n境資料；(三)本件家事聲請狀之越南文譯本各三份，逾期即駁回\n其訴。\n    理  由\n一、按原告之訴，有起訴不合程式或不備其他要件者，法院應以\n    裁定駁回之。但其情形可以補正者，審判長應定期間先命補\n    正，民事訴訟法第249條第1項第6款定有明文。又本國人提\n    起涉外民事訴訟事件，須使被告受有程序保障，即除送達之\n    適法性外，尚須使被告有了解可能性及適時性，如被告欠缺\n    本國語學能力，應附翻譯文，亦屬必備程式。\n二、本件被告朱氏萬為越南籍，原告提出之家事聲請狀未載有被\n    告送達地址，致本院無法送達訴訟文書，且未附國際通用性\n    語文或越南文譯本，均屬不符起訴之必備程式，於法不合，\n    應定期間命其補正。\n三、依家事事件法第51條、民事訴訟法第121條第1項，裁定如主\n    文。\n中    華    民    國   103    年    2     月    26    日\n                  家事法庭法官  法  官  <a href=\"https://www.pingluweb.com.tw/#!judgeDetail?id=50e3f67021129327c1d37929\" target=\"_blank\">黃永定</a>\n以上正本係照原本作成。\n本件裁定不得抗告。\n中    華    民    國   103    年    2     月    26    日\n                                書記官潘端典\n","courtCode":"KLD","fulltext":null,"gist":null,"identifier":"KLDV,103,家親聲,29,20140226,1-18737c31-7cfd-449f-9eda-a51dcf2cd0e4","issue":"改定監護人","jno":"29","jtype":"R","judgeDate":1393344000000,"jyear":103,"lastUpdate":1594296671409,"reportStatus":7,"source":"opendata","summary":null},"report":{"amount":0,"appellant":null,"appellantAgent":null,"appellantLawyer":null,"appellee":null,"appelleeAgent":null,"appelleeLawyer":null,"assignCounsel":null,"beJudgedPerson":null,"caseNum":["103,家親聲,29"],"caseType":"V","chosenCounsel":null,"clerk":"潘端典","codeNum":"家親聲","courtCode":"KLD","defendant":null,"defendantAgent":null,"defendantLawyer":null,"flag":false,"identifier":"KLDV,103,家親聲,29,20140226,1-18737c31-7cfd-449f-9eda-a51dcf2cd0e4","inmate":null,"interlocutoryPetitioner":null,"jno":"29","jtype":"R","judge":null,"judgeDate":1393344000000,"jyear":103,"lastUpdate":1594296671407,"lawyerCustomers":null,"level":1,"lose":null,"main":"原告應於本裁定送達後二十日內，補正：(一)與被告結婚之證明\n文件（上載有被告之越南住居所及年籍資料）；(二)被告之入出\n境資料；(三)本件家事聲請狀之越南文譯本各三份，逾期即駁回\n其訴。","money":0,"petitioner":["王秋川"],"petitionerAgent":null,"petitionerLawyer":null,"plaintiff":null,"plaintiffAgent":null,"plaintiffLawyer":null,"presideJudge":"黃永定","previousCaseNum":null,"previousCourtCode":null,"previousJudgeDate":null,"privateProsecutor":null,"proportion":0.0,"prosecutor":null,"publicDefender":null,"publicJudge":null,"puisne":null,"respondent":null,"result":1,"sentence":null,"statute":["民事訴訟法第121條第1項","民事訴訟法第249條第1項第6款"],"tags":null,"type":"民事裁定","win":null},"statute":[{"items":[{"cnum":"第一百二十一條第一項","num":"第121條第1項","val":121},{"cnum":"第二百四十九條第一項第六款","num":"第249條第1項第6款","val":249}],"statute":"民事訴訟法"}],"tags":null},"success":true}