{"lastError":"","response":{"reportBase":{"caseNum":"102,家非調,112","caseType":"V","codeNum":"家非調","content":"臺灣嘉義地方法院民事裁定　102年度家非調字第112號　　　　　　\n聲　請　人　侯志學　\n上列聲請人與陳美蘭間請求改定監護人事件，本院裁定如下：\n    主  文\n原告應於本裁定送達後7日內，補正起訴狀上相對人之真正住所\n或居所，或依法聲請公示送達，逾期即駁回其訴。\n    理  由          \n一、按當事人書狀，應記載當事人姓名、性別、年齡、職業及住\n    所或居所，當事人為法人或其他團體者，應記載其名稱及事\n    務所或營業所，民事訴訟法第116條第1款定有明文。\n二、本件原告起訴，未據於起訴狀上載明相對人陳美蘭之真正住\n    所或居所，或依法聲請公示送達，致無法送達文書，於法不\n    合，應定期間命其補正。\n三、依民事訴訟法第121條第1項裁定如主文。    \n中    華    民    國   102    年    10    月    2     日  \n                  家事庭  法  官  <a href=\"https://www.pingluweb.com.tw/#!judgeDetail?id=50e3f65d21129327c1d36e8e\" target=\"_blank\">康存真</a>          \n以上正本係照原本作成。\n中    華    民    國   102    年    10    月    2     日  \n                          書記官  洪筱喬\n","courtCode":"CYD","fulltext":null,"gist":null,"identifier":"CYDV,102,家非調,112,20131002,1-19f29def-aa69-4f4d-81c7-9107fee630a1","issue":"改定監護人","jno":"112","jtype":"R","judgeDate":1380643200000,"jyear":102,"lastUpdate":1594338599457,"reportStatus":7,"source":"opendata","summary":null},"report":{"amount":0,"appellant":null,"appellantAgent":null,"appellantLawyer":null,"appellee":null,"appelleeAgent":null,"appelleeLawyer":null,"assignCounsel":null,"beJudgedPerson":null,"caseNum":["102,家非調,112"],"caseType":"V","chosenCounsel":null,"clerk":"洪筱喬","codeNum":"家非調","courtCode":"CYD","defendant":null,"defendantAgent":null,"defendantLawyer":null,"flag":false,"identifier":"CYDV,102,家非調,112,20131002,1-19f29def-aa69-4f4d-81c7-9107fee630a1","inmate":null,"interlocutoryPetitioner":null,"jno":"112","jtype":"R","judge":null,"judgeDate":1380643200000,"jyear":102,"lastUpdate":1594338599457,"lawyerCustomers":null,"level":1,"lose":null,"main":"原告應於本裁定送達後7日內，補正起訴狀上相對人之真正住所\n或居所，或依法聲請公示送達，逾期即駁回其訴。","money":0,"petitioner":["侯志學"],"petitionerAgent":null,"petitionerLawyer":null,"plaintiff":null,"plaintiffAgent":null,"plaintiffLawyer":null,"presideJudge":"康存真","previousCaseNum":null,"previousCourtCode":null,"previousJudgeDate":null,"privateProsecutor":null,"proportion":0.0,"prosecutor":null,"publicDefender":null,"publicJudge":null,"puisne":null,"respondent":null,"result":1,"sentence":null,"statute":["民事訴訟法第116條第1款","民事訴訟法第121條第1項"],"tags":null,"type":"民事裁定","win":null},"statute":[{"items":[{"cnum":"第一百十六條第一款","num":"第116條第1款","val":116},{"cnum":"第一百二十一條第一項","num":"第121條第1項","val":121}],"statute":"民事訴訟法"}],"tags":null},"success":true}