{"lastError":"","response":{"reportBase":{"caseNum":"103,輔宣,26","caseType":"V","codeNum":"輔宣","content":"臺灣新北地方法院民事裁定　　　　　　 103年度輔宣字第26號\n聲　請　人　黃伯俊\n相　對　人\n即受輔助宣\n告人　　　　黃伯凱\n關　係　人　黃伯仁\n上列聲請人聲請改定輔助人事件，本院裁定如下：\n    主      文\n改定黃伯仁（男，民國四十五年八月六日生，身分證統一編號：\nZ000000000號）為受輔助宣告之人黃伯凱之輔助人。\n聲請費用由受輔助宣告之人黃伯凱負擔。\n    理      由\n一、本件聲請意旨略以：聲請人為相對人之胞弟，相對人因智能\n    不足等因素，經鈞院於民國102年8月30日以102年度監宣字\n    第572號裁定宣告為受輔助宣告之人，並選定聲請人黃伯俊\n    為輔助人。嗣聲請人黃伯俊近日因開早餐店做生意，相當勞\n    累，無法兼任照顧相對人，而關係人即相對人之長兄黃伯仁\n    即將辦理退休，有較多時間及能力照顧相對人，並經家人一\n    致同意改由關係人黃伯仁擔任相對人之輔助人，最能符合相\n    對人之最佳利益，為此請求改由黃伯仁擔任相對人之輔助人\n    等語。\n二、按受輔助宣告之人應置輔助人，民法第1113條之1第1項定有\n    明文。又法院選定監護人時，應依受監護宣告之人之最佳利\n    益，優先考量受監護宣告之人之意見，審酌一切情狀，並注\n    意下列事項：一、受監護宣告之人之身心狀態與生活及財產\n    狀況。二、受監護宣告之人與其配偶、子女或其他共同生活\n    之人間之情感狀況。三、監護人之職業、經歷、意見及其與\n    受監護宣告之人之利害關係。四、法人為監護人時，其事業\n    之種類與內容，法人及其代表人與受監護宣告之人之利害關\n    係；而有事實足認監護人不符受監護人之最佳利益，或有顯\n    不適任之情事者，法院得依受監護人、四親等內之親屬、檢\n    察官、主管機關或其他利害關係人之聲請，改定適當之監護\n    人；民法1111條之1、第1106條之1各定有明文。上開規定，\n    並依民法第1113條之1第2項規定於輔助人及有關輔助之職務\n    準用之。\n三、經查：聲請人主張之事實，業經聲請人黃伯俊到庭陳稱：因\n    為在做早餐店較忙碌，無法照顧相對人，伊另一位哥哥黃伯\n    仁願意擔任輔助人，且其他全部四兄弟也都同意改由黃伯仁\n    擔任輔助人，早餐店經營要早上四點多就起來，一直做到中\n    午等語甚詳（參見本院103年12月1日非訟事件筆錄），復據\n    其提出四兄弟即黃伯仁、黃伯仲、黃伯仙、黃伯俊出具之同\n    意書、戶籍謄本等件為證，堪認聲請人之主張為真。本院依\n    上開調查結果，認聲請人黃伯俊因經營早餐店，每天早上四\n    點到中午之時段，均須專注於店內之經營，而無力親自就相\n    對人之相關事務為輔助，其擔任相對人之輔助人確有不符合\n    相對人最佳利益之情事，並審酌關係人黃伯仁即將退休，且\n    有輔助相對人之意願及能力，並適於任之，是改定由黃伯仁\n    為受輔助宣告之人黃伯凱之輔助人，應能符合相對人之最佳\n    利益。\n四、依家事事件法第164條第2項，裁定如主文。\n中    華    民    國    103    年    12    月    9    日\n                  家事法庭  法  官  <a href=\"https://www.pingluweb.com.tw/#!judgeDetail?id=50e3f65b21129327c1d36cfb\" target=\"_blank\">劉大衛</a>\n正本係照原本作成。\n如不服本裁定，應於送達後十日內向本院提出抗告狀，並繳納抗\n告費新臺幣1千元。\n中    華    民    國    103    年    12    月    9    日\n                            書記官  沈菀玲\n","courtCode":"PCD","fulltext":null,"gist":null,"identifier":"PCDV,103,輔宣,26,20141209,1-26a2138d-7906-4a36-830e-97013b1e8e09","issue":"改定輔助人","jno":"26","jtype":"R","judgeDate":1418054400000,"jyear":103,"lastUpdate":1594352186781,"reportStatus":7,"source":"opendata","summary":null},"report":{"amount":0,"appellant":null,"appellantAgent":null,"appellantLawyer":null,"appellee":null,"appelleeAgent":null,"appelleeLawyer":null,"assignCounsel":null,"beJudgedPerson":null,"caseNum":["103,輔宣,26"],"caseType":"V","chosenCounsel":null,"clerk":"沈菀玲","codeNum":"輔宣","courtCode":"PCD","defendant":null,"defendantAgent":null,"defendantLawyer":null,"flag":false,"identifier":"PCDV,103,輔宣,26,20141209,1-26a2138d-7906-4a36-830e-97013b1e8e09","inmate":null,"interlocutoryPetitioner":null,"jno":"26","jtype":"R","judge":null,"judgeDate":1418054400000,"jyear":103,"lastUpdate":1594352186781,"lawyerCustomers":null,"level":1,"lose":null,"main":"改定黃伯仁（男，民國四十五年八月六日生，身分證統一編號：\nZ000000000號）為受輔助宣告之人黃伯凱之輔助人。\n聲請費用由受輔助宣告之人黃伯凱負擔。","money":0,"petitioner":["黃伯俊","告人黃伯凱","黃伯仁","即受輔助宣","相對人"],"petitionerAgent":null,"petitionerLawyer":null,"plaintiff":null,"plaintiffAgent":null,"plaintiffLawyer":null,"presideJudge":"劉大衛","previousCaseNum":null,"previousCourtCode":null,"previousJudgeDate":null,"privateProsecutor":null,"proportion":0.0,"prosecutor":null,"publicDefender":null,"publicJudge":null,"puisne":null,"respondent":null,"result":0,"sentence":null,"statute":["民法第1113條之1第2項","民法第1113條之1第1項"],"tags":null,"type":"民事裁定","win":null},"statute":[{"items":[{"cnum":"第一千一百十三條之一第二項","num":"第1113條之1第2項","val":1113},{"cnum":"第一千一百十三條之一第一項","num":"第1113條之1第1項","val":1113}],"statute":"民法"}],"tags":null},"success":true}