{"lastError":"","response":{"reportBase":{"caseNum":"102,監宣,551","caseType":"V","codeNum":"監宣","content":"臺灣臺北地方法院民事裁定　　　　　　102年度監宣字第551號\n聲　請　人　廖韻華\n代　理　人　白乃云律師\n　　　　　　鄧湘全律師\n相　對　人　廖俊雄\n法定代理人　廖駿銘\n代　理　人　林金鈴律師\n程序監理人　吳孟玲律師\n上列當事人間聲請改定監護人事件，本院裁定如下：\n    主  文\n聲請駁回。\n聲請程序費用由聲請人負擔。\n    理  由\n一、按有事實足認監護人不符受監護人之最佳利益，或有顯不適\n    任之情事者，法院得依受監護人、四親等內之親屬、檢察官\n    、主管機關或其他利害關係人之聲請，改定適當之監護人，\n    不受民法第1094條第1項規定之限制，此於成年人之監護準\n    用之，為民法第1106條之1第1項、第1113條所明定。是以，\n    聲請改定成年人之監護人，須以有事實足認監護人不符受監\n    護人之最佳利益，或監護人有顯不適任之情事者，始足當之\n    。\n二、本件聲請人主張其為相對人之胞姊，相對人前經臺灣板橋（\n    新北）地方法院95年度禁字第76號裁定宣告為禁治產人，選\n    定廖春來為監護人，廖春來於民國98年10月29日死亡，本院\n    依關係人廖駿銘聲請，以100年度監字第122號民事裁定選定\n    廖駿銘為相對人之監護人，並指定廖偉君為會同開具財產清\n    冊之人等情，業據其提出戶籍謄本、臺灣板橋地方法院95年\n    度禁字第76號民事裁定、本院100年度監字第122號民事裁定\n    為證（見本院卷（一）9至14頁），並據本院依職權調取本\n    院100年度監字第122號卷，核閱無誤，堪信為真。聲請人主\n    張監護人廖駿銘未實際照護相對人，亦不願聘請專業或合適\n    之看護人照顧相對人，每月領取相對人之財產新台幣（下同\n    ）5萬元作為照顧費用，揮霍或覬覦相對人之財產，對於相\n    對人之存款亦交待不清，損害相對人之權益，由其擔任監護\n    人不符相對人之最佳利益，並不適任監護人等情，固據其提\n    出照片為證（見本院卷（一）15至18頁）。惟查，廖駿銘係\n    相對人之養子，從事導遊工作，而相對人雖受監護宣告，但\n    身體健全，行動自如，料理生活，並無困難，雖獨居於西門\n    町，然廖駿銘及其家人均會隨時前往看顧，瞭解其生活狀況\n    ，已據廖駿銘陳明在卷（見本院卷（一）128至129頁）。本\n    院為相對人之利益，選任吳孟律師為相對人之程序監理人，\n    程序監理人提出報告略以：依廖駿銘提出之照片顯示，廖駿\n    銘經常帶相對人出遊，相對人在照片中之表情十分愉悅，且\n    廖駿銘及其家人對相對人之生活細節及喜好有清楚描述，另\n    按愛愛院之資料及人員表示，廖駿銘及其家人每週均有訪視\n    ，且互動良好。廖駿銘及其家人對相對人之互動應屬頻繁，\n    照顧並無不週情形。就情感交流部分，在程序監理人訪視相\n    對人時，相對人曾以點頭表示廖駿銘、廖偉君均有照顧伊，\n    在詢問「廖駿銘」、「廖偉君」之姓名時，相對人均有笑容\n    ，且不斷有肢體表示，然詢問「廖韻華」（以其日文名字稱\n    呼）及黃安琪之姓名時，從相對人之表情可推知，對該等姓\n    名並不熟悉。相對人與廖駿銘及其家人之關係係熟悉，且並\n    無交惡。廖駿銘為相對人之養子，在擔任相對人監護人期間\n    ，對監護人之身心及其他權利，並無不利之處。廖駿銘在現\n    金存款部分之管理上，或許有檢討的必要，但在照顧部分，\n    並無失責。相對人在愛愛院，該養護所之環境及護理人員均\n    屬優質，相對人之生活應無遭受不當對待之危險，只要聲請\n    人時常去院所探訪，應可卸下心中擔憂。又程序監理人就聲\n    請人與廖駿銘在年齡、身體狀況、經濟收入、關係狀態、過\n    往互動密切程度、與受監護人熟悉程度、至養護所後之關懷\n    程度、支持系統、照顧計畫、為受監理人管理財產之效能、\n    為受監理人管理財產之計畫為評估，聲請人為59分，廖駿銘\n    為63分，有卷附程序監理人法庭評估報告、補充意見書足參\n    （見本院卷（一）227至264頁、卷（二）70至75頁），並據\n    程序監理人陳明在卷（見本院卷（二）67頁）。足見廖駿銘\n    並無不適任之情形，聲請人與相對人雖為姊弟關係，然平常\n    少有互動，其與廖駿銘間之信賴關係亦不足，實難期兩人共\n    同為相對人之利益執行監護人之職務，而依程序監理人對雙\n    方之評比可知，由廖駿銘擔任相對人之監護人，亦顯然較優\n    於聲請人。至於廖駿銘在管理相對人現金部分，廖駿銘亦坦\n    言相對人帳戶內之現金，長期以來均由其管理，係家族公帳\n    和股票借名帳戶，在原監護人廖春來死亡後，為了減少往後\n    稅金之繳納，將現金轉出至其個人帳戶，現金合計約1700萬\n    元（見本院卷（二）66頁），此係廖駿銘在擔任相對人監護\n    人前之行為，廖駿銘經本院選定為監護人之後，亦不否認此\n    事實，則該款項究為家族公款，抑或相對人所有，因監護人\n    管理財產應以善良管理人之注意為之，是廖駿銘有召開家族\n    會議釐清款項歸屬之必要，如屬於相對人所有，亦應與會同\n    開具財產清冊之人將款項列冊陳報本院。而相對人每月之租\n    金收入，廖駿銘將部分用於相對人之生活開銷，部分用於家\n    屬代為照顧或安置之對價，尚難謂有何不當之處，且程序監\n    理人亦認未逾常情（見本院卷（二）74頁），則聲請人主張\n    廖駿銘非適任之監護人，聲請改定，並無理由，應予駁回。\n    爰裁定如主文。\n中    華    民    國    103    年    6    月    23    日\n                      家事法庭法  官  <a href=\"https://www.pingluweb.com.tw/#!judgeDetail?id=50e3f65c21129327c1d36dbc\" target=\"_blank\">吳素勤</a>\n以上正本係照原本作成。\n如不服本裁定應於送達後10日內向本院提出抗告狀，並繳納抗告\n費新臺幣1,000元。\n中    華    民    國    103    年    6    月    23    日\n                              書記官  郭麗琴\n","courtCode":"TPD","fulltext":null,"gist":null,"identifier":"TPDV,102,監宣,551,20140623,1-3af8258e-5672-4b84-83a1-9de27d796e87","issue":"改定監護人","jno":"551","jtype":"R","judgeDate":1403452800000,"jyear":102,"lastUpdate":1594343837509,"reportStatus":7,"source":"opendata","summary":null},"report":{"amount":0,"appellant":null,"appellantAgent":null,"appellantLawyer":null,"appellee":null,"appelleeAgent":null,"appelleeLawyer":null,"assignCounsel":null,"beJudgedPerson":null,"caseNum":["102,監宣,551"],"caseType":"V","chosenCounsel":null,"clerk":"郭麗琴","codeNum":"監宣","courtCode":"TPD","defendant":null,"defendantAgent":null,"defendantLawyer":null,"flag":false,"identifier":"TPDV,102,監宣,551,20140623,1-3af8258e-5672-4b84-83a1-9de27d796e87","inmate":null,"interlocutoryPetitioner":null,"jno":"551","jtype":"R","judge":null,"judgeDate":1403452800000,"jyear":102,"lastUpdate":1594343837507,"lawyerCustomers":null,"level":1,"lose":null,"main":"聲請駁回。\n聲請程序費用由聲請人負擔。","money":0,"petitioner":["廖韻華"],"petitionerAgent":null,"petitionerLawyer":["鄧湘全","白乃云","林金鈴"],"plaintiff":null,"plaintiffAgent":null,"plaintiffLawyer":null,"presideJudge":"吳素勤","previousCaseNum":null,"previousCourtCode":null,"previousJudgeDate":null,"privateProsecutor":null,"proportion":0.0,"prosecutor":null,"publicDefender":null,"publicJudge":null,"puisne":null,"respondent":null,"result":2,"sentence":null,"statute":["民法第1106條之1第1項","民法第1113條","民法第1094條第1項"],"tags":null,"type":"民事裁定","win":null},"statute":[{"items":[{"cnum":"第一千零九十四條第一項","num":"第1094條第1項","val":1094},{"cnum":"第一千一百零六條之一第一項","num":"第1106條之1第1項","val":1106},{"cnum":"第一千一百十三條","num":"第1113條","val":1113}],"statute":"民法"}],"tags":null},"success":true}