{"lastError":"","response":{"reportBase":{"caseNum":"102,監宣,622","caseType":"V","codeNum":"監宣","content":"臺灣臺北地方法院民事裁定　　　　　　102年度監宣字第622號\n聲　請　人　林張秀鑾\n代　理　人　林麗娟\n上列當事人間改定監護人事件，本院裁定如下：\n    主  文\n聲請駁回。\n聲請程序費用由聲請人負擔。\n    理  由\n一、按因非財產權關係為聲請者，徵收費用新臺幣（下同）1,00\n    0 元。關係人未預納者，法院應限期命其預納；逾其仍不預\n    納者，應駁回其聲請。家事事件法第97條準用非訟事件法第\n    14條第1項、第26條定有明文。\n二、本件聲請未依規定預納聲請費用，經本院通知應於民國102\n    年12月6 日庭期前內補正，於102 年11月19日送達，有卷附\n    送達證書、本院民事科查詢簡答表在卷足參，聲請人逾期迄\n    未補正，其聲請難認合法，應予駁回。爰裁定如主文。\n中    華    民    國   102    年    12    月    17    日\n                      家事法庭法  官  <a href=\"https://www.pingluweb.com.tw/#!judgeDetail?id=50e3f66921129327c1d3753c\" target=\"_blank\">藍家偉</a>\n以上正本係照原本作成。\n如不服本裁定應於送達後10日內向本院提出抗告狀，並繳納抗告\n費新臺幣1,000元。\n中    華    民    國   102    年    12    月    17    日\n                              書記官  蔡沛圻\n","courtCode":"TPD","fulltext":null,"gist":null,"identifier":"TPDV,102,監宣,622,20131217,1-4341c450-bfaf-4cbc-b53a-e4334b8079c0","issue":"改定監護人","jno":"622","jtype":"R","judgeDate":1387209600000,"jyear":102,"lastUpdate":1594340837520,"reportStatus":7,"source":"opendata","summary":null},"report":{"amount":0,"appellant":null,"appellantAgent":null,"appellantLawyer":null,"appellee":null,"appelleeAgent":null,"appelleeLawyer":null,"assignCounsel":null,"beJudgedPerson":null,"caseNum":["102,監宣,622"],"caseType":"V","chosenCounsel":null,"clerk":"蔡沛圻","codeNum":"監宣","courtCode":"TPD","defendant":null,"defendantAgent":null,"defendantLawyer":null,"flag":false,"identifier":"TPDV,102,監宣,622,20131217,1-4341c450-bfaf-4cbc-b53a-e4334b8079c0","inmate":null,"interlocutoryPetitioner":null,"jno":"622","jtype":"R","judge":null,"judgeDate":1387209600000,"jyear":102,"lastUpdate":1594340837520,"lawyerCustomers":null,"level":1,"lose":null,"main":"聲請駁回。\n聲請程序費用由聲請人負擔。","money":0,"petitioner":["林張秀鑾"],"petitionerAgent":["林麗娟"],"petitionerLawyer":null,"plaintiff":null,"plaintiffAgent":null,"plaintiffLawyer":null,"presideJudge":"藍家偉","previousCaseNum":null,"previousCourtCode":null,"previousJudgeDate":null,"privateProsecutor":null,"proportion":0.0,"prosecutor":null,"publicDefender":null,"publicJudge":null,"puisne":null,"respondent":null,"result":2,"sentence":null,"statute":[],"tags":null,"type":"民事裁定","win":null},"statute":[],"tags":null},"success":true}