{"lastError":"","response":{"reportBase":{"caseNum":"106,監宣,45","caseType":"V","codeNum":"監宣","content":"臺灣嘉義地方法院民事裁定　　　　　　 106年度監宣字第45號\n聲　請　人　蔡雅雲\n相　對　人　蔡義順\n關　係　人　蔡采燕\n上列當事人間請求改定監護人事件，本院裁定如下：\n    主    文\n改定蔡雅雲（女，民國六十五年十月三十日生，身分證統一編號\n：Z000000000號）為受監護宣告人蔡義順之監護人。\n指定蔡采燕（女，民國六十三年十一月十三日生，身分證統一編\n號：Z000000000號）為會同開具財產清冊之人。\n程序費用由受監護宣告之人蔡義順負擔。\n    理    由\n一、聲請意旨略以：聲請人蔡雅雲為蔡義順之次女，蔡義順於民\n    國96年11月12日經本院以96年度禁字第135號裁定宣告為禁\n    治產人，並由其配偶蔡陳蜜擔任監護人。因蔡陳蜜於106年2\n    月21日死亡，為蔡義順之利益，依法聲請選定聲請人為蔡義\n    順之監護人，並指定蔡采燕為會同開具財產清冊之人等語。\n二、按民法總則民國97年5月2日修正之條文施行前，已為禁治產\n    宣告者，視為已為監護宣告；次按民法規定之禁治產或禁治\n    產人，自民法總則中華民國97年5月2日修正之條文施行後，\n    一律改稱為監護或受監護宣告之人，民法總則施行法第4條\n    第2項前段、第4條之1定有明文；再按中華民國97年5月2日\n    修正之民法親屬編第4章條文施行前所設置之監護人，於修\n    正施行後，適用修正後之規定，民法親屬編施行法第14條之\n    2亦有明文。上開民法總則中華民國97年5月2日修正之條文\n    ，於98年11月23日施行，蔡義順已受禁治產宣告，依法視為\n    已為監護宣告，合先敘明。\n三、復按監護人死亡、經法院許可辭任或有民法第1096條各款情\n    形之一，且受監護人無民法第1094條第1項之監護人者，法\n    院得依受監護人、第1094條第3項聲請權人之聲請或依職權\n    ，另行選定適當之監護人，民法第1106條第1項定有明文。\n    末按法院為監護之宣告時，應依職權就配偶、四親等內之親\n    屬、最近1年有同居事實之其他親屬、主管機關、社會福利\n    機構或其他適當之人選定1人或數人為監護人，並同時指定\n    會同開具財產清冊之人，民法第1111條第1項亦定有明文。\n四、經查：\n  聲請人前揭主張，業據其提出同意書、戶籍謄本、蔡陳蜜除\n    戶謄本為證。因受監護宣告人蔡義順之監護人蔡陳蜜已死亡\n    ，參照前開規定，聲請人聲請改定為受監護宣告人之監護人\n    ，即屬有據。\n  本院審酌受監護宣告人蔡義順之父母及配偶均死亡，而聲請\n    人為受監護宣告人之次女，且有願意擔任本件之監護人，故\n    認由聲請人擔任受監護宣告人之監護人，應無不當之處，依\n    上開規定，改定聲請人擔任受監護宣告人蔡義順之監護人。\n    又聲請人既經本院選定為監護人，自應依民法第1112條規定\n    ，負責護養療治受監護宣告人之身體及妥善為財產管理之職\n    務。\n  另就指定會同開具財產清冊之人部分，聲請人聲請指定關係\n    人蔡采燕任之，審酌蔡采燕亦為受監護宣告人之長女，有意\n    願且無不適任之情，本院認由其擔任會同開具財產清冊之人\n    ，亦屬適當。依上開規定，指定蔡采燕為會同開具財產清冊\n    之人。又依民法第1113條準用同法第1099條之規定，於監護\n    開始時，監護人對於受監護宣告人之財產，應會同開具財產\n    清冊之人於2個月內開具財產清冊並陳報法院，在財產清冊\n    開具完成並陳報法院前，監護人對於受監護人之財產，僅得\n    為管理上必要之行為，併此敘明。\n五、依家事事件法第164條第2項，裁定如主文。\n中    華    民    國   106    年    5     月    3     日\n                    家事法庭    法  官  <a href=\"https://www.pingluweb.com.tw/#!judgeDetail?id=50e3f66521129327c1d372c6\" target=\"_blank\">洪挺梧</a>\n以上正本係照原本作成。\n如不服本裁定應於送達後10日內向本院提出抗告狀，並繳納抗告\n費新臺幣1,000元。\n中    華    民    國   106    年    5     月    3     日\n                                書記官  張菀純\n","courtCode":"CYD","fulltext":null,"gist":null,"identifier":"CYDV,106,監宣,45,20170503,1-47403f79-9acb-44a1-a9af-cc847d4c6b9e","issue":"改定監護人","jno":"45","jtype":"R","judgeDate":1493740800000,"jyear":106,"lastUpdate":1594581941116,"reportStatus":7,"source":"opendata","summary":null},"report":{"amount":0,"appellant":null,"appellantAgent":null,"appellantLawyer":null,"appellee":null,"appelleeAgent":null,"appelleeLawyer":null,"assignCounsel":null,"beJudgedPerson":null,"caseNum":["106,監宣,45"],"caseType":"V","chosenCounsel":null,"clerk":"張菀純","codeNum":"監宣","courtCode":"CYD","defendant":null,"defendantAgent":null,"defendantLawyer":null,"flag":false,"identifier":"CYDV,106,監宣,45,20170503,1-47403f79-9acb-44a1-a9af-cc847d4c6b9e","inmate":null,"interlocutoryPetitioner":null,"jno":"45","jtype":"R","judge":null,"judgeDate":1493740800000,"jyear":106,"lastUpdate":1594581941115,"lawyerCustomers":null,"level":1,"lose":null,"main":"改定蔡雅雲（女，民國六十五年十月三十日生，身分證統一編號\n：Z000000000號）為受監護宣告人蔡義順之監護人。\n指定蔡采燕（女，民國六十三年十一月十三日生，身分證統一編\n號：Z000000000號）為會同開具財產清冊之人。\n程序費用由受監護宣告之人蔡義順負擔。","money":0,"petitioner":["蔡雅雲","蔡采燕"],"petitionerAgent":null,"petitionerLawyer":null,"plaintiff":null,"plaintiffAgent":null,"plaintiffLawyer":null,"presideJudge":"洪挺梧","previousCaseNum":null,"previousCourtCode":null,"previousJudgeDate":null,"privateProsecutor":null,"proportion":0.0,"prosecutor":null,"publicDefender":null,"publicJudge":null,"puisne":null,"respondent":null,"result":0,"sentence":null,"statute":["民法第1112條","民法第1099條","民法第1111條第1項","民法第1113條","民法第1096條","民法第1094條第3項","民法第1094條第1項","民法第1106條第1項"],"tags":null,"type":"民事裁定","win":null},"statute":[{"items":[{"cnum":"第一千零九十四條第三項","num":"第1094條第3項","val":1094},{"cnum":"第一千零九十四條第一項","num":"第1094條第1項","val":1094},{"cnum":"第一千零九十六條","num":"第1096條","val":1096},{"cnum":"第一千零九十九條","num":"第1099條","val":1099},{"cnum":"第一千一百零六條第一項","num":"第1106條第1項","val":1106},{"cnum":"第一千一百十一條第一項","num":"第1111條第1項","val":1111},{"cnum":"第一千一百十二條","num":"第1112條","val":1112},{"cnum":"第一千一百十三條","num":"第1113條","val":1113}],"statute":"民法"}],"tags":null},"success":true}