{"lastError":"","response":{"reportBase":{"caseNum":"105,監宣,633","caseType":"V","codeNum":"監宣","content":"臺灣臺中地方法院民事裁定　　　　　　105年度監宣字第633號\n聲　請　人　陳鍊卿　\n　　　　　　陳廷鈺　\n相　對　人　陳蔡月裡\n關　係　人　陳鍊富　\n　　　　　　陳鍊永　\n　　　　　　陳櫻香　\n上列聲請人聲請改定受監護宣告人監護人事件，本院裁定如下：\n    主    文\n選任甲○○社會工作師為相對人之程序監理人。\n    理    由\n一、按於涉及受監護宣告人之事件時，法院認為有必要時，宜依\n    家事事件法第15條第1項、第2項規定選任程序監理人，家事\n    事件法審理細則第22條訂有明文。次按，法院得就社會福利\n    主管機關、社會福利機構所屬人員、律師公會、社會工作師\n    公會或其他相類似公會所推薦具有性別平權意識、尊重多元\n    文化，並有處理家事事件相關知識之適當人員，選任為程序\n    監理人，亦有同法第16條第1項規定可參。\n二、經查：相對人前因精神障礙，業經本院於民國101年12月26\n    日以101年度監宣字第475號民事裁定為受監護宣告之人，並\n    選定聲請人丁○○及關係人丙○○、戊○○為共同監護人，\n    關係人乙○○為會同開具財產清冊之人。而聲請人認關係人\n    丙○○有不適任相對人監護人之職之事由而聲請本件改定相\n    對人之監護人事件。本院認相對人意思能力欠缺，為相對人\n    之最佳利益，宜選任程序監理人。復經本院審酌社工督導甲\n    ○○係經司法院造冊之程序監理人人選，具有性別平權意識\n    、處理家事事件知識與實務工作經驗，及家庭系統動力智識\n    之實務工作經驗，足認由其擔任相對人之程序監理人，可充\n    分保障相對人之權益，復經甲○○社工督導同意擔任之，爰\n    依上開規定，裁定如主文。\n中    華    民    國   105    年    9     月    21    日\n                    家事法庭    法  官  <a href=\"https://www.pingluweb.com.tw/#!judgeDetail?id=50e3f66d21129327c1d37785\" target=\"_blank\">陳忠榮</a>\n正本係照原本作成。\n本件不得抗告。\n中    華    民    國   105    年    9     月    21    日\n                                書記官  廖日晟\n","courtCode":"TCD","fulltext":null,"gist":null,"identifier":"TCDV,105,監宣,633,20160921,1-517bf078-6db9-4cc3-895e-ca833d800e27","issue":"改定受監護宣告人監護人","jno":"633","jtype":"R","judgeDate":1474387200000,"jyear":105,"lastUpdate":1594577804307,"reportStatus":7,"source":"opendata","summary":null},"report":{"amount":0,"appellant":null,"appellantAgent":null,"appellantLawyer":null,"appellee":null,"appelleeAgent":null,"appelleeLawyer":null,"assignCounsel":null,"beJudgedPerson":null,"caseNum":["105,監宣,633"],"caseType":"V","chosenCounsel":null,"clerk":"廖日晟","codeNum":"監宣","courtCode":"TCD","defendant":null,"defendantAgent":null,"defendantLawyer":null,"flag":false,"identifier":"TCDV,105,監宣,633,20160921,1-517bf078-6db9-4cc3-895e-ca833d800e27","inmate":null,"interlocutoryPetitioner":null,"jno":"633","jtype":"R","judge":null,"judgeDate":1474387200000,"jyear":105,"lastUpdate":1594577804298,"lawyerCustomers":null,"level":1,"lose":null,"main":"選任甲○○社會工作師為相對人之程序監理人。","money":0,"petitioner":["陳鍊富","陳櫻香","陳廷鈺","陳鍊永","陳鍊卿"],"petitionerAgent":null,"petitionerLawyer":null,"plaintiff":null,"plaintiffAgent":null,"plaintiffLawyer":null,"presideJudge":"陳忠榮","previousCaseNum":null,"previousCourtCode":null,"previousJudgeDate":null,"privateProsecutor":null,"proportion":0.0,"prosecutor":null,"publicDefender":null,"publicJudge":null,"puisne":null,"respondent":null,"result":0,"sentence":null,"statute":[],"tags":null,"type":"民事裁定","win":null},"statute":[],"tags":null},"success":true}