{"lastError":"","response":{"reportBase":{"caseNum":"101,親,54","caseType":"V","codeNum":"親","content":"臺灣彰化地方法院民事裁定　　　　　　　 101年度親字第54號\n原　　　告　王孫玉英\n被　　　告　楊鈺琳\n上列當事人間停止親權並改定監護人事件，本院裁定如下：\n    主  文\n本件移送臺灣苗栗地方法院。\n    理  由\n一、按宣告停止親權或撤銷其宣告之訴，專屬行親權人或曾行親\n    權人住所地之法院管轄，民事訴訟法第592條定有明文。再\n    者，訴訟之全部或一部，法院認為無管轄權者，依原告聲請\n    或依職權以裁定移送其管轄法院，民事訴訟法第28條第1項\n    亦定有明文。\n二、經查，本件被告楊鈺琳住所地為苗栗縣竹南鎮○○里○○路\n    206號，有其戶籍謄本附卷可參。揆之前揭規定，本件專屬\n    於行親權人之住所地管轄，即應由被告住所地之法院即臺灣\n    苗栗地方法院管轄。從而，原告向無管轄權之本院起訴，與\n    上開規定不符，爰依職權以裁定移送其管轄法院。\n三、依民事訴訟法第28條第1項，裁定如主文。\n中    華    民    國   101    年    5     月    23    日\n                  家事法庭      法  官  <a href=\"https://www.pingluweb.com.tw/#!judgeDetail?id=50e3f66021129327c1d36fc1\" target=\"_blank\">施錫揮</a>\n以上正本係照原本作成。\n如對本裁定抗告須於裁定送達後10日內向本院提出抗告狀，並應\n繳納抗告費新台幣1000元整。\n中    華    民    國   101    年    5     月    23    日\n                                書記官  張俞文\n","courtCode":"CHD","fulltext":null,"gist":null,"identifier":"CHDV,101,親,54,20120523,1-544bb3e4-a212-453b-a7eb-6361ab38a2e0","issue":"停止親權並改定監護人","jno":"54","jtype":"R","judgeDate":1337702400000,"jyear":101,"lastUpdate":1594320472707,"reportStatus":7,"source":"opendata","summary":null},"report":{"amount":0,"appellant":null,"appellantAgent":null,"appellantLawyer":null,"appellee":null,"appelleeAgent":null,"appelleeLawyer":null,"assignCounsel":null,"beJudgedPerson":null,"caseNum":["101,親,54"],"caseType":"V","chosenCounsel":null,"clerk":"張俞文","codeNum":"親","courtCode":"CHD","defendant":["楊鈺琳"],"defendantAgent":null,"defendantLawyer":null,"flag":false,"identifier":"CHDV,101,親,54,20120523,1-544bb3e4-a212-453b-a7eb-6361ab38a2e0","inmate":null,"interlocutoryPetitioner":null,"jno":"54","jtype":"R","judge":null,"judgeDate":1337702400000,"jyear":101,"lastUpdate":1594320472707,"lawyerCustomers":null,"level":1,"lose":null,"main":"本件移送臺灣苗栗地方法院。","money":0,"petitioner":null,"petitionerAgent":null,"petitionerLawyer":null,"plaintiff":["王孫玉英"],"plaintiffAgent":null,"plaintiffLawyer":null,"presideJudge":"施錫揮","previousCaseNum":null,"previousCourtCode":null,"previousJudgeDate":null,"privateProsecutor":null,"proportion":0.0,"prosecutor":null,"publicDefender":null,"publicJudge":null,"puisne":null,"respondent":null,"result":0,"sentence":null,"statute":["民事訴訟法第592條","民事訴訟法第28條第1項"],"tags":null,"type":"民事裁定","win":null},"statute":[{"items":[{"cnum":"第二十八條第一項","num":"第28條第1項","val":28},{"cnum":"第五百九十二條","num":"第592條","val":592}],"statute":"民事訴訟法"}],"tags":null},"success":true}