{"lastError":"","response":{"reportBase":{"caseNum":"104,監宣,105","caseType":"V","codeNum":"監宣","content":"臺灣新北地方法院民事裁定　　　　　　104年度監宣字第105號\n聲　請　人\n即　監護人　羅益坤\n相　對　人\n即受監護宣\n告　　之人　羅阿木\n關　係　人　羅志強\n　　　　　　羅採鳳\n上列聲請人聲請另行選定監護人等事件，本院裁定如下：\n    主      文\n改定羅志強（男，民國00年0 月0 日生，身分證統一編號：Z000000000號）為受監護宣告之人羅阿木（男、民國00年00月00日生\n、身分證統一編號：Z000000000號）之監護人。\n指定羅採鳳（女，民國00年0 月0 日生，身分證統一編號：Z000000000號）為會同開具財產清冊之人。\n聲請費用由受監護宣告之人羅阿木負擔。\n    理      由\n一、按民法總則中華民國97年5月2日修正之條文施行前，已為禁\n    治產宣告者，視為已為監護宣告；繫屬於法院之禁治產事件\n    ，其聲請禁治產宣告者，視為聲請監護宣告；聲請撤銷禁治\n    產宣告者，視為聲請撤銷監護宣告；並均於修正施行後，適\n    用修正後之規定，民法總則施行法第4 條定有明文。上開按\n    民法總則中華民國97年5月2日修正之條文，於98年11月23日\n    施行，故禁治產人羅阿木（見卷附其戶籍謄本記事欄記載、\n    本院80年度禁字第26號裁定）應視為已受監護宣告，合先敘\n    明。\n二、按有事實足認監護人不符受監護人之最佳利益，或有顯不適\n    任之情事者，法院得依受監護人、四親等內之親屬、檢察官\n    、主管機關或其他利害關係人之聲請，改定適當之監護人，\n    不受第1094條第1項規定之限制；法院依第1094條第3項選定\n    監護人或依第1106條及第1106條之1另行選定或改定監護人\n    時，應同時指定會同開具財產清冊之人，民法第1106條之1\n    及第1094條第4項分別定有明文，並依民法第1113條規定於\n    成年人之監護準用之。次按法院選定監護人時，應依受監護\n    宣告之人之最佳利益，優先考量受監護宣告之人之意見，審\n    酌一切情狀，並注意下列事項：一受監護宣告之人之身心狀\n    態與生活及財產狀況。二受監護宣告之人與其配偶、子女或\n    其他共同生活之人間之情感狀況。三監護人之職業、經歷、\n    意見及其與受監護宣告之人之利害關係。四法人為監護人時\n    ，其事業之種類與內容，法人及其代表人與受監護宣告之人\n    之利害關係，民法1111 條 之1 復有明文。\n三、本件聲請意旨略以：聲請人羅益坤係相對人羅阿木之胞弟，\n    因聲請人之母羅邱妹前曾具狀向鈞院聲請宣告羅阿木為禁治\n    產人，業經鈞院於民國80年12月2 日以80年度禁字第26號裁\n    定宣告其為禁治產人在案，並由其母羅邱妹擔任監護人，惟\n    羅邱妹不幸於97年2 月25日死亡，嗣經鈞院以97年度監字第\n    136 號裁定改定由聲請人羅益坤擔任監護人。惟聲請人羅益\n    坤現年事已高，且常出國，顯已不適合擔任相對人羅阿木之\n    監護人，且相對人相關事務實際上皆由關係人羅志強協助處\n    理，家屬亦一致同意改由關係人羅志強擔任相對人羅阿木之\n    監護人，為考量羅阿木之權益維護，懇請鈞院裁定改由關係\n    人羅志強擔任相對人羅阿木之監護人，指定羅採鳳為會同開\n    具財產清冊之人等語。\n四、經查：聲請人主張之事實，業據提出同意書、親屬系統表、\n    戶籍謄本、中華民國身心障礙手冊影本、本院97年度監字第\n    136 號裁定影本等件為證，並經本院調閱80年度禁字第26號\n    、97年度監字第136 號卷宗核閱無訛，且聲請人羅益坤亦到\n    庭陳述：「有國有財產局的承租土地問題，常有一些事情要\n    辦，我又常出國，我認為由羅志強任監護人對相對人較好，\n    且我年紀也較大，換年輕人作較好」等語甚明（見本院104\n    年3 月9 日非訟事件筆錄），堪認聲請人之主張應為真實。\n    本院依上開調查結果，認監護人羅益坤因年紀較大，且常出\n    國，無暇妥適處理自相對人之相關事務，其擔任受監護宣告\n    之人羅阿木之監護人確有不符合受監護宣告之人羅阿木最佳\n    利益之情事，並審酌關係人羅志強為受監護宣告之人羅阿木\n    之姪子，有監護受監護宣告之人羅阿木之意願及能力，並適\n    於任之，是由關係人羅志強負責護養及照顧受監護宣告之人\n    並管理其財產，應能符合受監護宣告之人羅阿木之最佳利益\n    ，爰改定關係人羅志強為受監護宣告之人羅阿木之監護人。\n    另本院參酌關係人羅採鳳為受監護宣告之人羅阿木之胞妹，\n    爰依上揭規定，同時指定關係人羅採鳳為會同開具財產清冊\n    之人。\n五、又按監護人變更時，原監護人應即將受監護人之財產移交於\n    新監護人。受監護之原因消滅時，原監護人應即將受監護人\n    之財產交還於受監護人；如受監護人死亡時，交還於其繼承\n    人。前二項情形，原監護人應於監護關係終止時起二個月內\n    ，為受監護人財產之結算，作成結算書，送交新監護人、受\n    監護人或其繼承人。新監護人、受監護人或其繼承人對於前\n    項結算書未為承認前，原監護人不得免其責任。且按監護人\n    死亡時，前條移交及結算，由其繼承人為之；其無繼承人或\n    繼承人有無不明者，由新監護人逕行辦理結算，連同依第10\n    99條規定開具之財產清冊陳報法院。此分別為民法第1107條\n    及第1108條所明定。本件受監護宣告人羅阿木既經本院分別\n    改定由關係人羅志強任監護人及指定羅採鳳為會同開具財產\n    清冊之人，則原監護人羅益坤自應依上開規定，將受監護宣\n    告之人羅阿木之財產移交予新監護人羅志強，附此敘明。\n六、依家事事件法第164 條第2 項，裁定如主文。\n中    華    民    國   104    年    4     月    10    日\n                  家事法庭  法  官  <a href=\"https://www.pingluweb.com.tw/#!judgeDetail?id=50e3f65b21129327c1d36cfb\" target=\"_blank\">劉大衛</a>\n以上正本係照原本作成。\n如對本裁定抗告須於裁定送達後10日內向本院提出抗告狀，並繳\n納抗告費新臺幣1,000元。\n中    華    民    國   104    年    4     月    10    日\n                            書記官  沈菀玲\n","courtCode":"PCD","fulltext":null,"gist":null,"identifier":"PCDV,104,監宣,105,20150410,1-5e1b1aa8-d984-4832-aa63-8f5449d53e4c","issue":"改定監護人","jno":"105","jtype":"R","judgeDate":1428595200000,"jyear":104,"lastUpdate":1594564392713,"reportStatus":7,"source":"opendata","summary":null},"report":{"amount":0,"appellant":null,"appellantAgent":null,"appellantLawyer":null,"appellee":null,"appelleeAgent":null,"appelleeLawyer":null,"assignCounsel":null,"beJudgedPerson":null,"caseNum":["104,監宣,105"],"caseType":"V","chosenCounsel":null,"clerk":"沈菀玲","codeNum":"監宣","courtCode":"PCD","defendant":null,"defendantAgent":null,"defendantLawyer":null,"flag":false,"identifier":"PCDV,104,監宣,105,20150410,1-5e1b1aa8-d984-4832-aa63-8f5449d53e4c","inmate":null,"interlocutoryPetitioner":null,"jno":"105","jtype":"R","judge":null,"judgeDate":1428595200000,"jyear":104,"lastUpdate":1594564392712,"lawyerCustomers":null,"level":1,"lose":null,"main":"改定羅志強（男，民國00年0 月0 日生，身分證統一編號：Z000000000號）為受監護宣告之人羅阿木（男、民國00年00月00日生\n、身分證統一編號：Z000000000號）之監護人。\n指定羅採鳳（女，民國00年0 月0 日生，身分證統一編號：Z000000000號）為會同開具財產清冊之人。\n聲請費用由受監護宣告之人羅阿木負擔。","money":0,"petitioner":["即監護人羅益坤","即受監護宣","羅採鳳","相對人","羅志強"],"petitionerAgent":null,"petitionerLawyer":null,"plaintiff":null,"plaintiffAgent":null,"plaintiffLawyer":null,"presideJudge":"劉大衛","previousCaseNum":null,"previousCourtCode":null,"previousJudgeDate":null,"privateProsecutor":null,"proportion":0.0,"prosecutor":null,"publicDefender":null,"publicJudge":null,"puisne":null,"respondent":null,"result":0,"sentence":null,"statute":["民法第1113條","民法第1108條","民法第1106條之1","民法第1094條第4項","民法第1107條"],"tags":null,"type":"民事裁定","win":null},"statute":[{"items":[{"cnum":"第一千零九十四條第四項","num":"第1094條第4項","val":1094},{"cnum":"第一千一百零六條之一","num":"第1106條之1","val":1106},{"cnum":"第一千一百零七條","num":"第1107條","val":1107},{"cnum":"第一千一百零八條","num":"第1108條","val":1108},{"cnum":"第一千一百十三條","num":"第1113條","val":1113}],"statute":"民法"}],"tags":null},"success":true}