{"lastError":"","response":{"reportBase":{"caseNum":"105,監宣,248","caseType":"V","codeNum":"監宣","content":"臺灣新竹地方法院民事裁定　　　　　　105年度監宣字第248號\n聲　請　人　倪燦炎\n相　對　人　倪燦松\n關　係　人　王倪秀紅\n　　　　　　倪桂美\n　　　　　　倪燦溶\n　　　　　　倪慧伶\n　　　　　　倪明德\n　　　　　　游秋敏\n　　　　　　倪燦禮\n兼 上 一人　倪燦榮\n○　○　○　　　　　　0號\n上列聲請人聲請改定監護人事件，本院裁定如下：\n    主  文\n選定倪燦炎（男，民國00年0月00日生，身分證統一編號：Z000000000號）為受監護宣告人倪燦松之監護人。\n指定游秋敏（女，民國00年00月00日生，身分證統一編號﹕Z000000000號）為會同開具財產清冊之人。\n聲請程序費用新台幣壹仟元由相對人負擔。\n    理    由\n一、聲請意旨略以：聲請人為相對人之弟，相對人經本院以97年\n    度禁字第11號裁定宣告為禁治產人，而相對人之原監護人倪\n    來居、倪林月娥分別於民國105年1月13、105年10月22日死\n    亡，致現無監護人可為相對人處理相關事宜。為此，爰依法\n    提出本件聲請，請求為相對人選定監護人及指定會同開具財\n    產清冊之人等語。\n二、按民法總則中華民國97年5月2日修正之條文施行前，已為禁\n    治產宣告者，視為已為監護宣告，並於修正施行後，適用修\n    正後之規定；民法規定之禁治產或禁治產人，自修正施行後\n    ，一律改稱為監護或受監護宣告之人；施行前所設置之監護\n    人，於修正施行後，適用修正後之規定；修正之民法總則第\n    14條至第15條之2及民法親屬編第4章之規定，自公布後1年6\n    個月施行，民法總則施行法第4條第2項、第4條之1、第4條\n    之2、民法親屬編施行法第14條之2、第14條之3分別定有明\n    文。本件聲請人主張相對人前經本院97年度禁字第11號裁定\n    宣告為禁治產人，並由倪來居、倪林月娥任其監護人等情，\n    業據提出死亡證明為證，並經本院依職權調閱本院97年度禁\n    字第11號全卷核閱無訛，自堪認屬實。是依前開規定，自應\n    視為相對人已為監護之宣告，並應適用民法修正後之相關規\n    定，合先敘明。\n三、次按受監護宣告之人應置監護人；監護人死亡者，法院得依\n    受監護宣告之人、四親等內之親屬、檢察官、主管機關或其\n    他利害關係人之聲請，或依職權，另行選定適當之監護人，\n    此於成年人之監護亦有準用，此有民法第1110條、第1106條\n    第1項及第1113條規定可參。查相對人之原監護人倪來居、\n    倪林月娥已分別於105年1月13、105年10月22日死亡，聲請\n    人為相對人之弟乙節，有聲請人提出之死亡證明書、本院依\n    職權調閱之個人戶籍資料查詢結果在卷可佐，是聲請人既為\n    相對人之弟，自得依首揭規定，聲請為相對人另行選定監護\n    人。\n四、又按法院選定監護人時，應依職權就配偶、四親等內之親屬\n    、最近一年有同居事實之其他親屬、主管機關、社會福利機\n    構或其他適當之人選定一人或數人為監護人，並同時指定會\n    同開具財產清冊之人；再法院選定監護人時，應依受監護宣\n    告之人之最佳利益，優先考量受監護宣告之人之意見，審酌\n    一切情狀，並注意下列事項：受監護宣告之人之身心狀態\n    與生活及財產狀況。受監護宣告之人與其配偶、子女或其\n    他共同生活之人間之情感狀況。監護人之職業、經歷、意\n    見及其與受監護宣告之人之利害關係。法人為監護人時，\n    其事業之種類與內容，法人及其代表人與受監護宣告之人之\n    利害關係，此亦有民法第1111條第1項、第1111條之1規定可\n    參。經查，相對人無配偶、子女，父母皆已歿，而聲請人為\n    相對人之弟，與相對人同住，有擔任相對人監護人之意願，\n    另關係人王倪秀紅、倪桂美、倪燦榮、倪燦溶、倪燦禮為相\n    對人之兄、弟、妹，關係人倪慧伶為相對人之女，關係人倪\n    明德為相對人之兄倪燦坤（已去世）之子，均同意由聲請人\n    任相對人之監護人，有同意書及本院105年11月22日訊問筆\n    錄可參，而關係人等到庭均表示父母之前即已安排好，從而\n    ，本院參酌上開事證，認由聲請人為相對人之監護人，應能\n    符合相對人之利益，爰裁定如主文第一項所示。\n五、再按法院依民法第1094條第3項選定監護人或依第1106條及\n    第1106條之1另行選定或改定監護人時，應同時指定會同開\n    具財產清冊之人，民法第1094條第4項定有明文，且上開規\n    定依民法第1113條之規定，準用於成年人之監護。本院審酌\n    關係人游秋敏為相對人之弟媳，同意擔任會同開具財產清冊\n    之人，而關係人等對此亦表同意，有同意書可憑，本院依相\n    對人之最佳利益考量，並參酌上開規定意旨，認由游秋敏擔\n    任相對人之會同開具財產清冊之人，應無不妥，爰裁定如主\n    文第二項所示。又依同法第1099條之規定，於監護開始時，\n    監護人對於受監護宣告人倪燦松之財產，應會同游秋敏於二\n    個月內開具財產清冊並陳報法院，併此敘明。\n六、依家事事件法第164 條第2 項，裁定如主文。\n中    華    民    國   105    年    11    月    30    日\n                        家事法庭    法  官  <a href=\"https://www.pingluweb.com.tw/#!judgeDetail?id=50e3f66621129327c1d373c8\" target=\"_blank\">盧玉潤</a>\n以上正本係照原本作成。\n如對本裁定抗告須於裁定送達後10日內向本院提出抗告狀，並應\n繳納抗告費新台幣1,000 元。\n                                    書記官  陳明芳\n中    華    民    國   105    年    11    月    30    日\n","courtCode":"SCD","fulltext":null,"gist":null,"identifier":"SCDV,105,監宣,248,20161130,1-8a85d1bd-59fe-4ad1-bced-dd02089f2252","issue":"改定監護人","jno":"248","jtype":"R","judgeDate":1480435200000,"jyear":105,"lastUpdate":1594579491249,"reportStatus":7,"source":"opendata","summary":null},"report":{"amount":0,"appellant":null,"appellantAgent":null,"appellantLawyer":null,"appellee":null,"appelleeAgent":null,"appelleeLawyer":null,"assignCounsel":null,"beJudgedPerson":null,"caseNum":["105,監宣,248"],"caseType":"V","chosenCounsel":null,"clerk":"陳明芳","codeNum":"監宣","courtCode":"SCD","defendant":null,"defendantAgent":null,"defendantLawyer":null,"flag":false,"identifier":"SCDV,105,監宣,248,20161130,1-8a85d1bd-59fe-4ad1-bced-dd02089f2252","inmate":null,"interlocutoryPetitioner":null,"jno":"248","jtype":"R","judge":null,"judgeDate":1480435200000,"jyear":105,"lastUpdate":1594579491248,"lawyerCustomers":null,"level":1,"lose":null,"main":"選定倪燦炎（男，民國00年0月00日生，身分證統一編號：Z000000000號）為受監護宣告人倪燦松之監護人。\n指定游秋敏（女，民國00年00月00日生，身分證統一編號﹕Z000000000號）為會同開具財產清冊之人。\n聲請程序費用新台幣壹仟元由相對人負擔。","money":0,"petitioner":["倪慧伶","游秋敏","倪燦溶","王倪秀紅","倪燦炎","倪燦禮","倪明德","倪桂美"],"petitionerAgent":null,"petitionerLawyer":null,"plaintiff":null,"plaintiffAgent":null,"plaintiffLawyer":null,"presideJudge":"盧玉潤","previousCaseNum":null,"previousCourtCode":null,"previousJudgeDate":null,"privateProsecutor":null,"proportion":0.0,"prosecutor":null,"publicDefender":null,"publicJudge":null,"puisne":null,"respondent":null,"result":0,"sentence":null,"statute":["民法第1111條之1","民法第1110條","民法第1111條第1項","民法第1113條","民法第1094條第4項","民法第1106條之1","民法第1094條第3項","民法第1106條","民法第1106條第1項"],"tags":null,"type":"民事裁定","win":null},"statute":[{"items":[{"cnum":"第一千零九十四條第四項","num":"第1094條第4項","val":1094},{"cnum":"第一千零九十四條第三項","num":"第1094條第3項","val":1094},{"cnum":"第一千一百零六條之一","num":"第1106條之1","val":1106},{"cnum":"第一千一百零六條","num":"第1106條","val":1106},{"cnum":"第一千一百零六條第一項","num":"第1106條第1項","val":1106},{"cnum":"第一千一百十條","num":"第1110條","val":1110},{"cnum":"第一千一百十一條之一","num":"第1111條之1","val":1111},{"cnum":"第一千一百十一條第一項","num":"第1111條第1項","val":1111},{"cnum":"第一千一百十三條","num":"第1113條","val":1113}],"statute":"民法"}],"tags":null},"success":true}