{"lastError":"","response":{"reportBase":{"caseNum":"100,親,83","caseType":"V","codeNum":"親","content":"臺灣彰化地方法院民事裁定　100年度親字第83號\n原　　　告　童松\n原　　　告　童梁全\n被　　　告　阮垂粧\n上列當事人間停止親權並改定監護人事件，本院裁定如下：\n    主  文\n本件移送臺灣台中地方法院。\n    理  由\n一、按訴訟之全部或一部，法院認為無管轄權者，依原告聲請或\n    依職權以裁定移送於其管轄法院，民事訴訟法第28條第1項\n    定有明文。次按宣告停止親權或撤銷其宣告之訴，專屬行親\n    權人或曾行親權人住所地之法院管轄。民事訴訟法第592條\n    亦有明文。\n二、本件原告請求宣告被告停止親權之訴，經查被告目前住所地\n    係在台中市○區○○○街169號3樓之1，此有戶籍謄本及起\n    訴狀可稽，依民事訴訟法第592條之規定，自應由臺灣台中\n    地方法院管轄。茲原告向無管轄權之本院起訴，顯係違背專\n    屬管轄之規定，本院爰依職權將本件移送於該管轄法院。\n三、依首開法條裁定如主文。\n中    華    民    國   100    年    7     月    22    日\n                  家事法庭      法  官    <a href=\"https://www.pingluweb.com.tw/#!judgeDetail?id=50e3f66021129327c1d36fb4\" target=\"_blank\">施坤樹</a>\n以上正本係照原本作成。\n如對本裁定抗告須於裁定送達後10日內向本院提出抗告狀，並應\n繳納抗告費新台幣1000元。\n中    華    民    國   100    年    7     月    22    日\n                                書記官    許珍滋\n","courtCode":"CHD","fulltext":null,"gist":null,"identifier":"CHDV,100,親,83,20110722,1-aaf98f16-c538-461d-becc-0d931894a6e1","issue":"停止親權並改定監護人","jno":"83","jtype":"R","judgeDate":1311264000000,"jyear":100,"lastUpdate":1594308784980,"reportStatus":7,"source":"opendata","summary":null},"report":{"amount":0,"appellant":null,"appellantAgent":null,"appellantLawyer":null,"appellee":null,"appelleeAgent":null,"appelleeLawyer":null,"assignCounsel":null,"beJudgedPerson":null,"caseNum":["100,親,83"],"caseType":"V","chosenCounsel":null,"clerk":"許珍滋","codeNum":"親","courtCode":"CHD","defendant":["阮垂粧"],"defendantAgent":null,"defendantLawyer":null,"flag":false,"identifier":"CHDV,100,親,83,20110722,1-aaf98f16-c538-461d-becc-0d931894a6e1","inmate":null,"interlocutoryPetitioner":null,"jno":"83","jtype":"R","judge":null,"judgeDate":1311264000000,"jyear":100,"lastUpdate":1594308784979,"lawyerCustomers":null,"level":1,"lose":null,"main":"本件移送臺灣台中地方法院。","money":0,"petitioner":null,"petitionerAgent":null,"petitionerLawyer":null,"plaintiff":["童松","童梁全"],"plaintiffAgent":null,"plaintiffLawyer":null,"presideJudge":"施坤樹","previousCaseNum":null,"previousCourtCode":null,"previousJudgeDate":null,"privateProsecutor":null,"proportion":0.0,"prosecutor":null,"publicDefender":null,"publicJudge":null,"puisne":null,"respondent":null,"result":0,"sentence":null,"statute":["民事訴訟法第592條","民事訴訟法第28條第1項"],"tags":null,"type":"民事裁定","win":null},"statute":[{"items":[{"cnum":"第二十八條第一項","num":"第28條第1項","val":28},{"cnum":"第五百九十二條","num":"第592條","val":592}],"statute":"民事訴訟法"}],"tags":null},"success":true}