{"lastError":"","response":{"reportBase":{"caseNum":"104,監宣,1018","caseType":"V","codeNum":"監宣","content":"臺灣臺中地方法院民事裁定　　　　　 104年度監宣字第1018號　　　　　　　　　　　　　　　　　　　　　　　　　　　　　　　　　　　　　　　　　　　\n聲　請　人　謝培基\n受監護宣告\n之人　　　　謝凌\n上列聲請人聲請改定受監護宣告人監護人事件，本院裁定如下：\n    主    文\n選任楊銷樺律師為本件程序監理人。\n    理    由\n一、按於涉及受監護宣告人之事件時，法院認為有必要時，宜依\n    家事事件法第15條第1項、第2項規定選任程序監理人，家事\n    事件法審理細則第22條定有明文。次按，法院得就社會福利\n    主管機關、社會福利機構所屬人員、律師公會、社會工作師\n    公會或其他相類似公會所推薦具有性別平權意識、尊重多元\n    文化，並有處理家事事件相關知識之適當人員，選任為程序\n    監理人，亦有同法第16條第1項規定可參。\n二、經查，本件聲請人為受監護宣告人乙○○之長子，現以關係\n    人甲○○即乙○○之長女不適任乙○○之監護人為由，聲請\n    另行改定監護人，此為涉及受監護宣告人之事件，且本院認\n    為為乙○○之利益，有必要為其選任程序監理人。再經本院\n    審酌楊銷樺律師為經司法院造冊推薦之程序監理人人選，具\n    有處理家事事件知識及實務工作經驗，且向本院陳明同意擔\n    任本件程序監理人，聲請人亦同意上開程序監理人人選，此\n    有本院電話紀錄在卷可佐，據上，足認楊銷樺律師應為適當\n    之人選，爰依上揭規定，選任楊銷樺律師為乙○○之程序監\n    理人。\n三、爰裁定如主文。\n中    華    民    國   105    年    4     月    11    日\n                  家事法庭    法  官  <a href=\"https://www.pingluweb.com.tw/#!judgeDetail?id=50e3f65d21129327c1d36ea7\" target=\"_blank\">廖慧娟</a>  \n以上正本係照原本作成。\n本裁定不得抗告。\n中    華    民    國   105    年    4     月    11    日\n                              書記官  王薇葶\n","courtCode":"TCD","fulltext":null,"gist":null,"identifier":"TCDV,104,監宣,1018,20160411,1-ad2eb17f-4a89-4557-b60e-79b516077bf5","issue":"改定受監護宣告人監護人","jno":"1018","jtype":"R","judgeDate":1460304000000,"jyear":104,"lastUpdate":1594575240595,"reportStatus":7,"source":"opendata","summary":null},"report":{"amount":0,"appellant":null,"appellantAgent":null,"appellantLawyer":null,"appellee":null,"appelleeAgent":null,"appelleeLawyer":null,"assignCounsel":null,"beJudgedPerson":null,"caseNum":["104,監宣,1018"],"caseType":"V","chosenCounsel":null,"clerk":"王薇葶","codeNum":"監宣","courtCode":"TCD","defendant":null,"defendantAgent":null,"defendantLawyer":null,"flag":false,"identifier":"TCDV,104,監宣,1018,20160411,1-ad2eb17f-4a89-4557-b60e-79b516077bf5","inmate":null,"interlocutoryPetitioner":null,"jno":"1018","jtype":"R","judge":null,"judgeDate":1460304000000,"jyear":104,"lastUpdate":1594575240595,"lawyerCustomers":null,"level":1,"lose":null,"main":"選任楊銷樺律師為本件程序監理人。","money":0,"petitioner":["受監護宣告","謝培基"],"petitionerAgent":null,"petitionerLawyer":null,"plaintiff":null,"plaintiffAgent":null,"plaintiffLawyer":null,"presideJudge":"廖慧娟","previousCaseNum":null,"previousCourtCode":null,"previousJudgeDate":null,"privateProsecutor":null,"proportion":0.0,"prosecutor":null,"publicDefender":null,"publicJudge":null,"puisne":null,"respondent":null,"result":0,"sentence":null,"statute":[],"tags":null,"type":"民事裁定","win":null},"statute":[],"tags":null},"success":true}