{"lastError":"","response":{"reportBase":{"caseNum":"101,監宣,148","caseType":"V","codeNum":"監宣","content":"臺灣彰化地方法院民事裁定　　　　　　101年度監宣字第148號\n聲　請　人　陳腰\n　　　　　　陳義博\n　　　　　　陳阿麵\n　　　　　　薛陳美玉\n受監護宣告之人\n　　　　　　陳聰明\n上列聲請人聲請改定監護人事件，本院裁定如下：\n    主  文\n改定薛陳美玉（民國○○年○○月○○日生、國民身分證號碼：Ｚ\n000000000號）為受監護宣告之人陳聰明（民國○○年○○月○日生，\n國民身分證號碼：Ｚ000000000號）之監護人。\n聲請人其餘聲請駁回。\n聲請程序費用新台幣壹仟元由受監護宣告之人陳聰明負擔。\n    理  由\n一、本件聲請意旨略以：聲請人陳腰為受監護宣告之人陳聰明\n    （民國○○年○○月○日生，國民身分證號碼：Ｚ000000000號）\n    之母，陳聰明前經臺灣桃園地方法院98年度禁字第217號裁\n    定宣告為禁治產人，當時並以聲請人陳腰為當然監護人（\n    按即法定監護人）。然因聲請人陳腰年事已高，今已88歲\n    ，除行動不便外，近來更診斷出罹有糖尿病、腎病變、心律\n    不整等症狀，實已不適再任照顧陳聰明之責，經聲請人陳\n    腰與陳聰明之兄、姐即聲請人陳義博、陳阿麵及薛陳美玉討\n    論後，同意改由與聲請人陳腰、受監護宣告之人陳聰明同\n    住之聲請人薛陳美玉為監護人，以利日後事務之處理，爰依\n    法請求改定監護人及指定陳義博為會同開具財產清冊之人等\n    語。\n二、按依民法總則施行法第4條第2項、民法親屬編施行法第14條\n    之2規定，中華民國（下同）97年5月2日修正之條文施行前\n    ，已為禁治產宣告者，視為已為監護宣告，並於修正施行後\n    ，適用修正後之規定；97年5月2日修正之民法親屬編第4章\n    條文施行前所設置之監護人，於修正施行後，適用修正後之\n    規定。又97年5月2日修正民法總則第14條至第15條之2、親\n    屬編第4章之規定，均自公布後1年6個月施行，此觀之民法\n    總則編施行法第4條之2、親屬編施行法第14條之3規定自明\n    。查上揭修正條文已經總統於97年5月23日以華總一義字第\n    09700059171號令公布，是自於98年11月23日起生效施行。\n    復按之民法第1113條準用同法第1106條之1第1項規定，有事\n    實足認監護人不符受監護人之最佳利益，或有顯不適任之情\n    事者，法院得依前條第1項聲請權人之聲請，改定適當之監\n    護人，不受第1094條第1項規定之限制。\n三、經查，聲請人主張陳聰明前經臺灣桃園地方法院98年度禁字\n    第217號裁定宣告為禁治產人，當時並以聲請人陳腰為法\n    定監護人，而聲請人等分係陳聰明之兄、姐等情，業據提出\n    該民事裁定影本1件及戶籍謄本4件為憑，堪信為真實。次查\n    ，聲請人陳腰係13年4月22日生，罹有糖尿病、腎病變、\n    心律不整等症狀乙節，業據提出戶籍謄本及診斷證明書可佐\n    ，是聲請人陳腰主張其已不適再任照顧陳聰明之責等語，\n    亦可採信。茲原監護人陳腰既因年齡老邁，健康不佳，而\n    無法勝任照顧受監護宣告之人陳聰明之事務，顯可認不符受\n    監護宣告之人陳聰明之最佳利益，是聲請人等據而聲請改定\n    監護人，於法自屬有據，應予准許。\n四、復按之民法第1111條之1規定，「法院選定監護人時，應依\n    受監護宣告之人之最佳利益，優先考量受監護宣告之人之意\n    見，審酌一切情狀，並注意下列事項：一、受監護宣告之人\n    之身心狀態與生活及財產狀況。二、受監護宣告之人與其配\n    偶、子女或其他共同生活之人間之情感狀況。三、監護人之\n    職業、經歷、意見及其與受監護宣告之人之利害關係。四、\n    法人為監護人時，其事業之種類與內容，法人及其代表人與\n    受監護宣告之人之利害關係。」。本院審酌聲請人薛陳美玉\n    與與受監護宣告之人陳聰明係姐弟關係，與陳聰明同戶居住\n    ，關係密切，且查其財產豐厚，有房屋、土地、投資等多筆\n    ，並經本院依職權調閱其稅務電子閘門財產所得調件明細表\n    附卷可考，聲請人等4人復具狀一致同意由薛陳美玉任監護\n    人，足認改定聲請人薛陳美玉任受監護宣告之人陳聰明之監\n    護人，應符合其最佳利益，爰裁定如主文第1項所示。另本\n    院前依聲請人等4人之聲請，裁定指定聲請人陳義博為會同\n    開具財產清冊之人，有聲請人提出本院100年度監字第136號\n    民事裁定影本足佐，聲請人於本件重複聲請本院裁定指定聲\n    請人陳義博為會同開具財產清冊之人，自無必要，應予駁回\n    ，爰裁定如主文第2項所示。\n五、依家事事件法第164條第2項，裁定如主文。\n中    華    民    國  101    年    7        月    31  日\n                    家事法庭法  官  <a href=\"https://www.pingluweb.com.tw/#!judgeDetail?id=50e3f66721129327c1d373f7\" target=\"_blank\">簡燕子</a>\n以上正本係照原本作成。\n如對本裁定抗告，須於裁定送達後10日之不變期間內，向本院提\n出抗告狀，並繳納抗告費新臺幣1,000元。\n中    華    民    國  101    年    7        月    31  日\n                            書記官  洪年慶\n","courtCode":"CHD","fulltext":null,"gist":null,"identifier":"CHDV,101,監宣,148,20120731,1-b296254f-d976-414f-81ca-3fade1bf3068","issue":"改定監護人","jno":"148","jtype":"R","judgeDate":1343664000000,"jyear":101,"lastUpdate":1594323200152,"reportStatus":7,"source":"opendata","summary":null},"report":{"amount":0,"appellant":null,"appellantAgent":null,"appellantLawyer":null,"appellee":null,"appelleeAgent":null,"appelleeLawyer":null,"assignCounsel":null,"beJudgedPerson":null,"caseNum":["101,監宣,148"],"caseType":"V","chosenCounsel":null,"clerk":"洪年慶","codeNum":"監宣","courtCode":"CHD","defendant":null,"defendantAgent":null,"defendantLawyer":null,"flag":false,"identifier":"CHDV,101,監宣,148,20120731,1-b296254f-d976-414f-81ca-3fade1bf3068","inmate":null,"interlocutoryPetitioner":null,"jno":"148","jtype":"R","judge":null,"judgeDate":1343664000000,"jyear":101,"lastUpdate":1594323200151,"lawyerCustomers":null,"level":1,"lose":null,"main":"改定薛陳美玉（民國○○年○○月○○日生、國民身分證號碼：Ｚ\n000000000號）為受監護宣告之人陳聰明（民國○○年○○月○日生，\n國民身分證號碼：Ｚ000000000號）之監護人。\n聲請人其餘聲請駁回。\n聲請程序費用新台幣壹仟元由受監護宣告之人陳聰明負擔。","money":0,"petitioner":["陳義博","薛陳美玉","陳聰明","陳腰","陳阿麵"],"petitionerAgent":null,"petitionerLawyer":null,"plaintiff":null,"plaintiffAgent":null,"plaintiffLawyer":null,"presideJudge":"簡燕子","previousCaseNum":null,"previousCourtCode":null,"previousJudgeDate":null,"privateProsecutor":null,"proportion":0.0,"prosecutor":null,"publicDefender":null,"publicJudge":null,"puisne":null,"respondent":null,"result":2,"sentence":null,"statute":["民法第1111條之1","民法第1106條之1第1項","民法第1113條"],"tags":null,"type":"民事裁定","win":null},"statute":[{"items":[{"cnum":"第一千一百零六條之一第一項","num":"第1106條之1第1項","val":1106},{"cnum":"第一千一百十一條之一","num":"第1111條之1","val":1111},{"cnum":"第一千一百十三條","num":"第1113條","val":1113}],"statute":"民法"}],"tags":null},"success":true}