{"lastError":"","response":{"reportBase":{"caseNum":"103,監宣,215","caseType":"V","codeNum":"監宣","content":"臺灣臺南地方法院民事裁定　　　　　　103年度監宣字第215號\n聲　請　人　臺南市政府 \n法定代理人　賴清德　 住同上\n代　理　人　沈0含　 住臺南市○○區○○路00號\n上列聲請人聲請改定受監護宣告人監護人事件，本院裁定如下：\n    主      文\n改定臺南市政府社會局為受監護宣告人陳0武（男，民國00年0月\n00日生，身分證統一編號：Z000000000號）之監護人。\n指定臺南市政府所指派之人為會同開具財產清冊之人。\n聲請費用由受監護宣告之人陳0武負擔。\n    理      由\n一、本件聲請意旨略以：聲請人係受監護宣告人陳0武之監護人\n    ，並經鈞院於民國101年11月28日裁定確定，惟考量本市社\n    會局已為一級機關，為利執行受監護宣告人陳0武監護工作\n    事宜，及本局協處受監護宣告人陳0武監護後續服務之時效\n    ，爰聲請改由臺南市政府社會局擔任受監護宣告人陳0武之\n    監護人，俾利日後代為處理其相關事務等語。\n二、經查，受監護宣告人陳0武前經本院以101年度監宣字第85號\n    、101年度家聲抗字第9號裁定選定臺南市政府為其監護人之\n    事實，業經本院依職權調閱上開案卷查核屬實，堪予認定。\n    又聲請人雖為受監護宣告人陳0武之監護人，惟相關監護事\n    務均係由社會局處理，且社會局已為一級機關，為利於受監\n    護宣告人陳0武監護事務之處理時效，而為本件聲請一節，\n    亦經聲請人到庭陳述明確，並有聲請人所提臺南市政府組織\n    自治條例、臺南市政府社會局組織規程在卷可稽，是基於受\n    監護宣告人陳0武之最佳利益考量，認聲請人聲請改由臺南\n    市政府社會局擔任陳0武之監護人，應屬適當，爰依聲請人\n    之聲請裁定如主文第1項所示，並依民法第1094條第4項之規\n    定，指定臺南市政府所指派之人為會同開具財產清冊之人。\n三、依家事事件法第164條第2項，裁定如主文。\n中    華    民    國   103    年    7     月    24    日\n                  家事法庭法  官  <a href=\"https://www.pingluweb.com.tw/#!judgeDetail?id=50e3f66221129327c1d371b1\" target=\"_blank\">林育幟</a>\n以上正本係照原本作成。\n如不服本裁定，應於送達後10日內向本院提出抗告狀，並繳納抗\n告費新臺幣1,000元。\n中    華    民    國   103    年    7     月    24    日\n                          書記官  陳世明\n","courtCode":"TND","fulltext":null,"gist":null,"identifier":"TNDV,103,監宣,215,20140724,1-c9da5101-897d-4aab-9d2c-28f6547a3bc9","issue":"改定受監護宣告人監護人","jno":"215","jtype":"R","judgeDate":1406131200000,"jyear":103,"lastUpdate":1594347300265,"reportStatus":7,"source":"opendata","summary":null},"report":{"amount":0,"appellant":null,"appellantAgent":null,"appellantLawyer":null,"appellee":null,"appelleeAgent":null,"appelleeLawyer":null,"assignCounsel":null,"beJudgedPerson":null,"caseNum":["103,監宣,215"],"caseType":"V","chosenCounsel":null,"clerk":"陳世明","codeNum":"監宣","courtCode":"TND","defendant":null,"defendantAgent":null,"defendantLawyer":null,"flag":false,"identifier":"TNDV,103,監宣,215,20140724,1-c9da5101-897d-4aab-9d2c-28f6547a3bc9","inmate":null,"interlocutoryPetitioner":null,"jno":"215","jtype":"R","judge":null,"judgeDate":1406131200000,"jyear":103,"lastUpdate":1594347300265,"lawyerCustomers":null,"level":1,"lose":null,"main":"改定臺南市政府社會局為受監護宣告人陳0武（男，民國00年0月\n00日生，身分證統一編號：Z000000000號）之監護人。\n指定臺南市政府所指派之人為會同開具財產清冊之人。\n聲請費用由受監護宣告之人陳0武負擔。","money":0,"petitioner":["臺南市政府"],"petitionerAgent":["沈含"],"petitionerLawyer":null,"plaintiff":null,"plaintiffAgent":null,"plaintiffLawyer":null,"presideJudge":"林育幟","previousCaseNum":null,"previousCourtCode":null,"previousJudgeDate":null,"privateProsecutor":null,"proportion":0.0,"prosecutor":null,"publicDefender":null,"publicJudge":null,"puisne":null,"respondent":null,"result":0,"sentence":null,"statute":["民法第1094條第4項"],"tags":null,"type":"民事裁定","win":null},"statute":[{"items":[{"cnum":"第一千零九十四條第四項","num":"第1094條第4項","val":1094}],"statute":"民法"}],"tags":null},"success":true}