{"lastError":"","response":{"reportBase":{"caseNum":"103,監宣,260","caseType":"V","codeNum":"監宣","content":"臺灣新竹地方法院民事裁定　　　　　　103年度監宣字第260號\n聲　請　人　林獻界　\n代　理　人　彭火炎律師\n相對人即受　\n監護宣告人　林獻章　\n關　係　人　林淑英　\n　　　　　　林秀梅　\n上　一　人　　　　　　 \n代　理　人　南雪貞律師\n上列當事人間改定監護人事件，本院裁定如下：\n    主  文\n選任張秀菊律師為本件應受監護宣告之人丁○○之程序監理人，\n並由聲請人丙○○、關係人乙○○、甲○○分別預納程序監理人\n酬金新臺幣壹萬元、貳仟伍佰元、貳仟伍佰元。\n    理  由\n一、按民法總則中華民國97年5月2日修正之條文施行前，已為禁\n    治產宣告者，視為已為監護宣告，並於修正施行後，適用修\n    正後之規定；民法規定之禁治產或禁治產人，自修正施行後\n    ，一律改稱為監護或受監護宣告之人；修正之民法總則第14\n    條至第15條之2之規定，自公布後1年6個月施行。中華民國\n    97年5月2日修正之民法親屬編第四章條文施行前所設置之監\n    護人，於修正施行後，適用修正後之規定，民法總則施行法\n    第4條第2項、第4條之1、第4條之2、民法親屬編施行法第14\n    條之2規定甚明。查本件聲請人丙○○（下稱聲請人）主張\n    相對人丁○○（下稱相對人）前於民國95年8月22日經本院\n    以95年度禁字第74號民事裁定宣告為禁治產人等情，業據聲\n    請人提出該裁定影本為證，並經本院調取上開案卷核閱無誤\n    ，則於上開民法修正生效施行後，相對人應視為已為監護宣\n    告，並應適用民法修正後關於監護之相關規定。\n二、次按於涉及受監護宣告人之事件時，法院認為有必要時，宜\n    依家事事件法第15條第1項、第2項規定選任程序監理人，家\n    事事件法審理細則第22條定有明文。再按，法院得就社會福\n    利主管機關、社會福利機構所屬人員、律師公會、社會工作\n    師公會或其他相類似公會所推薦具有性別平權意識、尊重多\n    元文化，並有處理家事事件相關知識之適當人員，選任為程\n    序監理人，亦有同法第16條第1項規定可參。經查，本件聲\n    請人為相對人之胞兄，現以相對人即受監護宣告人之原監護\n    人即相對人之母林蔡水鳳業於99年8月31日辭世，現無監護\n    人為由，聲請選定相對人之監護人，有其所提死亡證明書及\n    除戶謄本為據，此為涉及受監護宣告人之事件，且本院認為\n    基於為相對人即受監護宣告人之利益，有必要為相對人選任\n    程序監理人。茲經本院審酌新竹律師公會推薦之張秀菊律師\n    具有法律專業知識與能力，並陳明願擔任本件程序監理人，\n    足認其應為適當之人選，可資就相對人情形何人適合擔任監\n    護人及何人適合擔任本件會同開具財產清冊之人等表示適當\n    之意見，茲依上開規定，選任張秀菊律師為本件相對人即受\n    監護宣告之人之程序監理人。又本件程序監理人之報酬，聲\n    請人及關係人乙○○、甲○○均到庭陳明願由聲請人預納新\n    台幣（下同）1萬元，關係人乙○○、甲○○則各預納2千5\n    百元等語（見本院103年12月4日訊問筆錄），是本院為使程\n    序順利進行，茲依家事事件法第16條第5項及程序監理人選\n    任及酬金支給辦法第14條第1項之規定，併諭知上揭報酬，\n    應由聲請人及關係人乙○○、甲○○等2人先行預納之，爰\n    裁定如主文所示。\n中    華    民    國   103    年    12    月    8     日\n               家事法庭  法      官  <a href=\"https://www.pingluweb.com.tw/#!judgeDetail?id=50e3f66221129327c1d37117\" target=\"_blank\">林建鼎</a>                                                                                      \n本裁定不得抗告。\n以上正本係照原本作成。\n中    華    民    國   103    年    12    月    8     日\n                         書  記  官  徐佩鈴\n","courtCode":"SCD","fulltext":null,"gist":null,"identifier":"SCDV,103,監宣,260,20141208,1-d7ae9951-7867-450d-b4dc-6a89d079a2cf","issue":"改定監護人","jno":"260","jtype":"R","judgeDate":1417968000000,"jyear":103,"lastUpdate":1594352950829,"reportStatus":7,"source":"opendata","summary":null},"report":{"amount":0,"appellant":null,"appellantAgent":null,"appellantLawyer":null,"appellee":null,"appelleeAgent":null,"appelleeLawyer":null,"assignCounsel":null,"beJudgedPerson":null,"caseNum":["103,監宣,260"],"caseType":"V","chosenCounsel":null,"clerk":"徐佩鈴","codeNum":"監宣","courtCode":"SCD","defendant":null,"defendantAgent":null,"defendantLawyer":null,"flag":false,"identifier":"SCDV,103,監宣,260,20141208,1-d7ae9951-7867-450d-b4dc-6a89d079a2cf","inmate":null,"interlocutoryPetitioner":null,"jno":"260","jtype":"R","judge":null,"judgeDate":1417968000000,"jyear":103,"lastUpdate":1594352950828,"lawyerCustomers":null,"level":1,"lose":null,"main":"選任張秀菊律師為本件應受監護宣告之人丁○○之程序監理人，\n並由聲請人丙○○、關係人乙○○、甲○○分別預納程序監理人\n酬金新臺幣壹萬元、貳仟伍佰元、貳仟伍佰元。","money":0,"petitioner":["林獻界"],"petitionerAgent":["相對人即受"],"petitionerLawyer":["南雪貞","彭火炎"],"plaintiff":null,"plaintiffAgent":null,"plaintiffLawyer":null,"presideJudge":"林建鼎","previousCaseNum":null,"previousCourtCode":null,"previousJudgeDate":null,"privateProsecutor":null,"proportion":0.0,"prosecutor":null,"publicDefender":null,"publicJudge":null,"puisne":null,"respondent":null,"result":0,"sentence":null,"statute":[],"tags":null,"type":"民事裁定","win":null},"statute":[],"tags":null},"success":true}