{"lastError":"","response":{"reportBase":{"caseNum":"107,監宣,107","caseType":"V","codeNum":"監宣","content":"臺灣花蓮地方法院民事裁定　　　　　　107年度監宣字第107號\n聲　請　人　林秋葉\n相　對　人　陳鑾英\n關　係　人　林進財\n　　　　　　游聖華\n上列當事人間聲請改定監護人事件，本院裁定如下：\n    主  文\n改定林秋葉為受監護宣告之人林進財之監護人。\n指定游聖華為會同開具財產清冊之人。\n聲請程序費用由受監護宣告之人林進財負擔。\n    理  由\n一、本件聲請意旨略以：關係人林進財前因精神分裂症，致不能\n    處理自己事務，於民國89年3月31日經本院以89年度禁字第9\n    號裁定宣告為禁治產人，相對人則因係林進財之母而當然成\n    為林進財之監護人；現陳鑾英90歲，年事已高，不堪勝任監\n    護人之職，為林進財之最佳利益，爰依法請求准許改定聲請\n    人林秋葉（林進財之胞妹）為林進財之監護人，並依修正後\n    民法之規定，指定關係人游聖華（林秋葉之長女）為會同開\n    具財產清冊之人等語。\n二、按受監護宣告之人應置監護人；法院為監護之宣告時，應依\n    職權就配偶、四親等內之親屬、最近1年有同居事實之其他\n    親屬、主管機關、社會福利機構或其他適當之人選定1人或\n    數人為監護人，並同時指定會同開具財產清冊之人，法院為\n    前項選定及指定前，得命主管機關或社會福利機構進行訪視\n    ，提出調查報告及建議，監護之聲請人或利害關係人亦得提\n    出相關資料或證據，供法院斟酌；又法院選定監護人時，應\n    依受監護宣告之人之最佳利益，優先考量受監護宣告之人之\n    意見，審酌一切情狀，並注意下列事項：受監護宣告之人\n    之身心狀態與生活及財產狀況。受監護宣告之人與其配偶\n    、子女或其他共同生活之人間之情感狀況。監護人之職業\n    、經歷、意見及其與受監護宣告之人之利害關係。法人為\n    監護人時，其事業之種類與內容，法人及其代表人與受監護\n    宣告之人之利害關係，民法第1110條、第1111條、第1111之\n    1條分別定有明文。次按民法第1106條之1規定：「有事實足\n    認監護人不符受監護人之最佳利益，或有顯不適任之情事者\n    ，法院得依前條第1項聲請權人之聲請，改定適當之監護人\n    ，不受第1094條第1項規定之限制。法院於改定監護人確定\n    前，得先行宣告停止原監護人之監護權，並由當地社會福利\n    主管機關為其監護人。」，此項規定為成年人監護所準用，\n    民法第1113條亦有明文。\n三、經查，聲請人主張之前揭事實，業據其提出戶籍謄本3件、\n    身分證影本2件為證，並經本院依職權調閱89年度禁字第9號\n    民事聲請事件卷宗查核屬實，堪信為真實。本院審酌陳鑾英\n    已屆90歲之高齡，行動不便，語言部分也只通原住民母語，\n    ，其對本院於調查期日之詢問，亦只趴在桌上，未為任何回\n    應，堪信確有難以勝任監護人職責之情事（見本院卷第18頁\n    反面）；而聲請人林秋葉為受監護宣告之人林進財之胞妹，\n    其有意願擔任林進財之監護人，經評估亦有監護林進財之能\n    力（花蓮縣社會工作師公會107年10月5日花社公會慧宣字第\n    107062號函附成年人之監護宣告案件之訪視評估報告參照）\n    ，爰依民法第1113條準用同法第1106條之1規定，改定聲請\n    人林秋葉錦為受監護宣告之人之監護人。復參酌關係人游聖\n    華為受監護宣告之人林進財之外甥女，其亦有意願協助聲請\n    人處理林進財之事務，爰依民法第1113條準用同法第1094第\n    4項規定，指定關係人游聖華為會同開具財產清冊之人。\n四、依家事事件法第164條第2項，裁定如主文。\n中    華    民    國   107    年    10    月    10    日\n                   家事法庭     法  官   <a href=\"https://www.pingluweb.com.tw/#!judgeDetail?id=50e3f65c21129327c1d36e07\" target=\"_blank\">周健忠</a>\n以上正本係照原本作成。\n如對本裁定抗告，須於裁定送達後10日之不變期間內，向本院提\n出抗告狀，並繳納抗告費新臺幣1,000元。\n中    華    民    國   107    年    10    月    11    日\n                                書記官   宋瑋陵\n","courtCode":"HLD","fulltext":null,"gist":null,"identifier":"HLDV,107,監宣,107,20181010,1-d81b5075-a168-47fa-9b71-bdd992a1c61c","issue":"改定監護人","jno":"107","jtype":"R","judgeDate":1539100800000,"jyear":107,"lastUpdate":1594623916429,"reportStatus":7,"source":"opendata","summary":null},"report":{"amount":0,"appellant":null,"appellantAgent":null,"appellantLawyer":null,"appellee":null,"appelleeAgent":null,"appelleeLawyer":null,"assignCounsel":null,"beJudgedPerson":null,"caseNum":["107,監宣,107"],"caseType":"V","chosenCounsel":null,"clerk":"宋瑋陵","codeNum":"監宣","courtCode":"HLD","defendant":null,"defendantAgent":null,"defendantLawyer":null,"flag":false,"identifier":"HLDV,107,監宣,107,20181010,1-d81b5075-a168-47fa-9b71-bdd992a1c61c","inmate":null,"interlocutoryPetitioner":null,"jno":"107","jtype":"R","judge":null,"judgeDate":1539100800000,"jyear":107,"lastUpdate":1594623916428,"lawyerCustomers":null,"level":1,"lose":null,"main":"改定林秋葉為受監護宣告之人林進財之監護人。\n指定游聖華為會同開具財產清冊之人。\n聲請程序費用由受監護宣告之人林進財負擔。","money":0,"petitioner":["林進財","林秋葉","游聖華"],"petitionerAgent":null,"petitionerLawyer":null,"plaintiff":null,"plaintiffAgent":null,"plaintiffLawyer":null,"presideJudge":"周健忠","previousCaseNum":null,"previousCourtCode":null,"previousJudgeDate":null,"privateProsecutor":null,"proportion":0.0,"prosecutor":null,"publicDefender":null,"publicJudge":null,"puisne":null,"respondent":null,"result":0,"sentence":null,"statute":["民法第1111條","民法第1110條","民法第1113條","民法第1106條之1","民法第1094條第1項"],"tags":null,"type":"民事裁定","win":null},"statute":[{"items":[{"cnum":"第一千零九十四條第一項","num":"第1094條第1項","val":1094},{"cnum":"第一千一百零六條之一","num":"第1106條之1","val":1106},{"cnum":"第一千一百十條","num":"第1110條","val":1110},{"cnum":"第一千一百十一條","num":"第1111條","val":1111},{"cnum":"第一千一百十三條","num":"第1113條","val":1113}],"statute":"民法"}],"tags":null},"success":true}