{"lastError":"","response":{"reportBase":{"caseNum":"101,監宣,194","caseType":"V","codeNum":"監宣","content":"臺灣彰化地方法院民事裁定　　　　　　101年度監宣字第194號\n聲　請　人　林宗遠\n相　對　人　林錫鉦\n關　係　人　林宗霖\n　　　　　　林束卿\n　　　　　　林秀勳\n　　　　　　林盟惠\n上列聲請人聲請改定監護人事件，本院裁定如下：\n    主    文\n選定林宗遠（男、民國○○年○月○日生、身分證統一編號：Ｚ00000\n0000號）為受監護宣告之人林錫鉦（男、民國○○年○月○○日生、\n身分證統一編號：Ｚ000000000號）之監護人。\n指定林束卿（女、民國○○年○○月○○日生、身分證統一編號：Ｚ000\n000000號）為會同開具財產清冊之人。\n聲請程序費用新台幣壹仟元由受監護宣告人林錫鉦負擔。\n    理  由\n一、聲請意旨略以：聲請人係相對人之胞弟，相對人前經貴院98\n    年度禁字第2號裁定宣告為禁治產人。惟原法定監護人即相\n    對人之父林立於民國101年4月6日死亡。相對人之其他家屬\n    達成共識由聲請人擔任相對人之監護人，為此爰請求選定聲\n    請人為相對人之監護人，及指定相對人之胞姐林束卿為會同\n    開具財產清冊之人，以利日後代為處理事務等語。\n二、按民法總則中華民國97年5月2日修正之條文施行前，已為禁\n    治產宣告者，視為已為監護宣告；繫屬於法院之禁治產事件\n    ，其聲請禁治產宣告者，視為聲請監護宣告；聲請撤銷禁治\n    產宣告者，視為聲請撤銷監護宣告；並均於修正施行後，適\n    用修正後之規定，民法總則施行法第4條定有明文。上開民\n    法總則中華民國97年5月2日修正之條文，98年11月23日施行\n    ，故相對人林錫鉦視為已受監護宣告，合先敘明。\n三、又按法院為監護之宣告時，應依職權就配偶、四親等內之親\n    屬、最近一年有同居事實之其他親屬、主管機關、社會福利\n    機構或其他適當之人選定一人或數人為監護人，並同時指定\n    會同開具財產清冊之人；法院選定監護人時，應依受監護宣\n    告之人之最佳利益，優先考量受監護宣告之人之意見，審酌\n    一切情狀，並注意下列事項：一、受監護宣告之人之身心狀\n    態與生活及財產狀況。二、受監護宣告之人與其配偶、子女\n    或其他共同生活之人間之情感狀況。三、監護人之職業、經\n    歷、意見及其與受監護宣告之人之利害關係。四、法人為監\n    護人時，其事業之種類與內容，法人及其代表人與受監護宣\n    告之人之利害關係，民法第1111條1項、第1111條之1均定有\n    明文。查聲請人主張相對人係聲請人之兄，相對人前經本院\n    於98年2月13日以98年度禁字第2號裁定准許宣告為禁治產人\n    ，由林立任相對人之監護人，然林立已於民國101年4月6日\n    亡故等情，業據聲請人提出戶籍謄本、戶口名簿影本、本院\n    98年度禁字第2號民事裁定為據，堪信屬實，是聲請人聲請\n    選定相對人之監護人，即屬正當。本院審酌聲請人林宗遠為\n    受監護宣告人之胞弟，關係人林束卿為受監護宣告人之胞姐\n    ，有上揭戶口名簿影本及戶籍謄本在卷可按；又聲請人林宗\n    遠以書狀表示建議本院選任其為相對人之監護人，並經相對\n    人之其他兄弟姐妹林宗霖、林束卿、林秀勳、林盟惠於本院\n    調查時到庭表示希望由林宗遠擔任相對人之監護人；而上開\n    相對人之其他兄弟姐妹並表示希望由關係人即相對人之胞姐\n    林束卿擔任會同開具財產清冊之人，亦獲關係人林束卿當庭\n    就此表示同意擔任等語明確，有本院訊問筆錄在卷可稽；是\n    本院參酌前揭各節，認由聲請人林宗遠任監護人，最能符合\n    受監護宣告之人之最佳利益，爰選定聲請人林宗遠為監護人\n    ；並指定關係人林束卿為會同開具財產清冊之人，爰裁定如\n    主文。\n四、爰依家事事件法第164條第2項，裁定如主文。\n中    華    民    國    101    年    9    月    14    日\n                  家事法庭      法  官  <a href=\"https://www.pingluweb.com.tw/#!judgeDetail?id=50e3f66621129327c1d37383\" target=\"_blank\">王美惠</a>\n以上正本係照原本作成。\n如對本裁定抗告須於裁定送達後10日內向本院提出抗告狀，並應\n繳納抗告費新台幣1000元整。\n中    華    民    國    101    年    9    月    14    日\n                                書記官  林憲男\n","courtCode":"CHD","fulltext":null,"gist":null,"identifier":"CHDV,101,監宣,194,20120914,1-df181b5f-7d80-431a-accc-6ac740813dcc","issue":"改定監護人","jno":"194","jtype":"R","judgeDate":1347552000000,"jyear":101,"lastUpdate":1594325860485,"reportStatus":7,"source":"opendata","summary":null},"report":{"amount":0,"appellant":null,"appellantAgent":null,"appellantLawyer":null,"appellee":null,"appelleeAgent":null,"appelleeLawyer":null,"assignCounsel":null,"beJudgedPerson":null,"caseNum":["101,監宣,194"],"caseType":"V","chosenCounsel":null,"clerk":"林憲男","codeNum":"監宣","courtCode":"CHD","defendant":null,"defendantAgent":null,"defendantLawyer":null,"flag":false,"identifier":"CHDV,101,監宣,194,20120914,1-df181b5f-7d80-431a-accc-6ac740813dcc","inmate":null,"interlocutoryPetitioner":null,"jno":"194","jtype":"R","judge":null,"judgeDate":1347552000000,"jyear":101,"lastUpdate":1594325860484,"lawyerCustomers":null,"level":1,"lose":null,"main":"選定林宗遠（男、民國○○年○月○日生、身分證統一編號：Ｚ00000\n0000號）為受監護宣告之人林錫鉦（男、民國○○年○月○○日生、\n身分證統一編號：Ｚ000000000號）之監護人。\n指定林束卿（女、民國○○年○○月○○日生、身分證統一編號：Ｚ000\n000000號）為會同開具財產清冊之人。\n聲請程序費用新台幣壹仟元由受監護宣告人林錫鉦負擔。","money":0,"petitioner":["林宗遠","林宗霖","林束卿","林秀勳","林盟惠"],"petitionerAgent":null,"petitionerLawyer":null,"plaintiff":null,"plaintiffAgent":null,"plaintiffLawyer":null,"presideJudge":"王美惠","previousCaseNum":null,"previousCourtCode":null,"previousJudgeDate":null,"privateProsecutor":null,"proportion":0.0,"prosecutor":null,"publicDefender":null,"publicJudge":null,"puisne":null,"respondent":null,"result":0,"sentence":null,"statute":["民法第1111條","民法第1111條之1"],"tags":null,"type":"民事裁定","win":null},"statute":[{"items":[{"cnum":"第一千一百十一條","num":"第1111條","val":1111},{"cnum":"第一千一百十一條之一","num":"第1111條之1","val":1111}],"statute":"民法"}],"tags":null},"success":true}