{"lastError":"","response":{"reportBase":{"caseNum":"99,監,124","caseType":"V","codeNum":"監","content":"臺灣嘉義地方法院民事裁定　　　　　　　 99年度監字第124號\n聲　請　人　丙○○　\n代　理　人　○○○律師\n相　對　人　丁○○　\n代　理　人　○○○律師　\n上列當事人間聲請改定監護人事件，本院裁定如下：\n    主  文\n聲請人關於改定監護之聲請駁回。\n兩造所生未成年子女甲○○（女、民國00年0月00日生）、次女\n乙○○（女、民國00年0月0日生）權利義務之行使或負擔，仍由\n兩造共同任之，並於就讀國中前由聲請人照顧同住，相對人得依\n附表所示之方式、時間與甲○○、乙○○會面交往。\n相對人應自本裁定確定之日起，分別至長女甲○○、次女乙○○\n成年之日止，於其等與聲請人同住期間，負擔長女甲○○、次女\n乙○○之扶養費用每人每月各新台幣柒仟伍佰元，並按月於每月\n十日前交付予聲請人代為管理支用，如相對人遲誤一期履行者，\n其後之期間視為亦已到期。\n聲請費用由聲請人負擔。\n    理  由\n一、聲請意旨略以：\n、兩造未婚同居，育有未成年長女甲○○（民國00年0月00日\n    出生）、次女乙○○（民國00年0月0日出生），聲請人分別\n    於民國○○年○月○日及○○年○月○日認領，就二名未成\n    年子女監護權協議由兩造共同行使，惟於生下次女乙○○不\n    久後，相對人因另有交往對象，而與聲請人協議分手，分手\n    後相對人將二名子女交由聲請人養育即行蹤成迷，迄今約有\n    3至4年未前來探視女兒或以電話關心女兒。相對人頗有資力\n    ，卻未提供分毫金錢撫養2名女兒，相對人名義上共同監護2\n    名女兒，但自離開後從未盡保護教養之義務，目前2名女兒\n    即將進入學齡期，相關就學資料或經費補助依規定要另一名\n    監護人即相對人的簽署，但相對人下落不明，影響未成年子\n    女的權益，請為未成年子女的利益，改定由聲請人單獨行使\n    或負擔對未成年女之權利、義務。\n、2名未成年子女若改定由聲請人行使權利、負擔義務，請鈞\n    院依行政院主計處「平均每人月消費支出（按區域別分）」\n    之標準命相對人給付扶養費，嘉義地區近年平均每人每月消\n    費支出約為新台幣15,000元，由聲請人與相對人各負擔二分\n    之一，相對人每月應給付各7,500元予未成年子女至其成年\n    為止，且交付監護人即聲請人代為管理使用，並命若遲誤一\n    期履行者，其後之期間視為亦已到期。\n、對財團法人○○○○○○○○○○○○○○○○基金會所為\n    之訪視報告內容無意見，依報告書調查內容，2名女兒仍由\n    聲請人監護為宜；對○○政府委託○○○○○○○○關懷協\n    會之訪視報報告，表示意見如下：、該報告就不知之事實\n    驟下判斷，憑一面之詞竟認定「聲請人之所以欲取得監護權\n    之目的在於要求金錢給付」、「聲請人一再向相對人家中長\n    輩借款，在改定監護聲請書上，除誣指相對人行蹤成迷」、\n    「聲請人在出庭前都會脅迫兩未成年人做不實之陳述」等等\n    ，足見訪視之社工立場偏頗，該報告內容不公正客觀；、\n    聲請人一開始向法扶基金會申請扶助，僅就改定監護權部分\n    為申請，代理人於接案後，著眼於一次訴訟解決眾多爭議及\n    相對人有相當資力應共同負擔扶養費之角度，建議聲請人增\n    加請求未成年子女扶養費，不是相對人及社工指稱「聲請人\n    是為了金錢給付才要求監護權」；、該報告未訪視過聲請\n    人、未看過未成年子女的生活環境，又怎能知悉聲請人會分\n    身乏術、無法妥善照顧兩未成年人？故○○○○該報告出於\n    片面、偏執、故意曲解、自我臆測所為之評估及建議，實不\n    值得參酌。\n、對相對人抗辯所為之陳述：\n、相對人所稱「2名子女於97年至99年間有返回相對人○○家\n    中約5至6次，○○年○月2名子女尚在相對人處由相對人照\n    顧」云云，但相對人並未據實託出事實原貌。實則，兩造分\n    手後，相對人不曾至○○探視或打電話關心2名女兒，相對\n    人斷了音訊行蹤成迷，只能在網路無名小站間接聯絡，聲請\n    人為顧及相對人祖父○○愛曾孫之情，在兩造分手後曾數度\n    帶2名女兒至○○○○住處，讓女兒待1天、3天或一星期不\n    等，但每次接送都未見相對人在家陪伴或照顧女兒，返家後\n    問女兒「媽媽是否有回來看你們、陪你們？」，女兒表示沒\n    有，○○年7月暑假期間，聲請人再送2名女兒至○○，一如\n    以往未看見相對人在家，小孩在○○住了3星期，但相對人\n    同樣未返家與女兒同住，僅有帶女兒出去購物、買零食，足\n    見2名女兒在○○期間大都是○○及外傭在照顧，相對人怎\n    敢說有盡保護教養義務？聲請人瞭解○○疼愛2名曾孫之情\n    ，但○○已近80歲，與2名女兒差了3代，再無法親力親為照\n    顧、教養2名年幼稚女，相對人實則自己無監護意願，是為\n    了祖父才爭監護權，然而不論依法定監護順位或為2名女兒\n    的最佳利益，聲請人較○○更優先、更適當任2名女兒之監\n    護人。\n、相對人稱其自○○年○月起任職於○○○○股份有限公司擔\n    任行政人員，並提出在職證明書為證，惟相對人應僅是健保\n    掛在○○○○公司，實際未在該公司任職，因兩造同居期間\n    ，相對人從不曾至公司、行號上班，○○年間兩造還曾共同\n    經營關東煮店，相對人大部分時間在顧店，怎麼分身去別的\n    公司上班？相對人之父為上市公司○○公司（○○紙類）的\n    負責人，要找一個關係企業或上下游公司開出相對人的在職\n    證明，實易如反掌。\n、聲請人承認曾毆打過相對人，聲請人事後相當後悔，聲請人\n    當時年輕、衝動，生活屢遭困境，包括弟弟死亡、獨自一人\n    要兼顧工作及照顧出生僅數月之長女（相對人生下長女後，\n    其家人突然將相對人帶走），相對人父親對聲請人提告妨害\n    家庭罪、經營事業失敗、負債等，聲請人在生活諸般壓力下\n    出現暴力行為，然而相對人亦有負面行為，例如：女兒哭鬧\n    時竟勒住女兒的脖子、摔壞手機等，加深兩造相處時之裂痕\n    ，聲請人與目前同居女友原是鄰居，當時相對人棄聲請人而\n    去時，係女友無怨無悔代為照顧兩造長女，兩造分手後，聲\n    請人才與女友慢慢發展感情。\n、相對人及相對人父親固然資力雄厚，但保護教養子女不應只\n    考慮金錢因素，相對人決意離開後，某日在聲請人要求下，\n    拿女兒的鞋來還，相對人看到許久未見的女兒，也不抱女兒\n    ，當時聲請人身上僅剩700元，不夠買女兒的奶粉，聲請人\n    開口請相對人先借一些錢買奶粉，相對人斷然拒絕，且稱「\n    伊的錢和現任男朋友的錢放在一起，伊不能隨便花」，相對\n    人當時完全不會在意女兒過得好不好，更何況數年後的今日\n    ？而聲請人在同居女友協助下，已渡過最艱難的階段，生活\n    愈來愈穩定，2名女兒在聲請人及同居女友的照顧下健康地\n    成長，2名女兒已習慣、適應隨同聲請人生活，對聲請人有\n    安全、信賴感，與同居女友的感情深厚，實不宜讓2名女兒\n    再改變居住環境或更換主要照顧者，聲請人每月收入約為4\n    萬餘元，若再加上政府社會福利補助，一家人生活應不虞匱\n    乏。\n、相對人固在庭上表達若爭取到監護權，會遷回○○親自照顧\n    未成年子女云云，但其言堪疑。蓋相對人自承目前在○○生\n    活，也自承與聲請人同居期間曾在○○市擺攤販售○○，惟\n    相對人提出之服務證明書記載其自○○年9月迄今任職於位\n    於○○○○鄉之○○○○公司，顯然虛偽！是以，不能排除\n    相對人為了訴訟才做出承諾，訴訟終結後會故態復萌將未成\n    年子女交由其祖父及外傭照顧。\n、2名未成年子女皆當庭表達想與聲請人同住或不願遷移至○\n    ○居住之意願，聲請人同居人○○已照顧2名未成年子女多\n    年，2名未成年子女與○○建立良好關係，也稱呼為「媽咪\n    」，為未成年子女之最佳利益，仍應由聲請人擔任監護人，\n    至於相對人探視時間及方式，聲請人願意做最大配合。\n、並聲明：、改定由聲請人行使或負擔對於未成年長女甲○\n    ○及次女乙○○之權利義務；、相對人應自裁定確定之日\n    起至甲○○成年之日即○○年○○月○○日止，按月給付7,\n    500元，並於每月10日前交付予法定代理人即聲請人代為管\n    理使用，相對人如遲誤一期履行者，其後之期間視為亦已到\n    期；、相對人應自裁定確定之日起至乙○○成年之日即11\n    4年7月7日止，按月給付7,500元，並於每月10日前交付予法\n    定代理人即聲請人代為管理使用，相對人如遲誤一期履行者\n    ，其後之期間視為亦已到期；、聲請費用由相對人負擔。\n二、相對人則抗辯以：\n、兩造於○○年間原為男女朋友關係，進而共同生活，相對人\n    先後生下長女甲○○、次女乙○○。惟兩造共同生活期間，\n    相對人因屢遭聲請人毆打，因此即使已育有二名子女，相對\n    人因恐懼聲請人之暴力行為，始終無法與聲請人論及婚嫁。\n    又因聲請人無固定工作收入，共同生活期間，兩造之生活費\n    及子女扶養費均由相對人負擔。惟於95年間聲請人竟另結新\n    歡，96年間三人曾同住一處，相對人無法接受聲請人坐享齊\n    人之福，及不堪聲請人之暴力行為，於97年初決意與聲請人\n    分手，並將兩名子女帶回○○照顧，嗣於97年初，聲請人假\n    借為子女過生日為由，將二名子女自相對人處帶回○○，相\n    對人為念及子女均可與父母接觸互動，同意二名子女由兩造\n    輪流照顧，而自97年至99年間，二名子女有返回相對人○○\n    家中約五、六次，聲請人亦多次前來相對人家中，與相對人\n    之祖父○○見面，於99年7月間二名子女尚在相對人處由相\n    對人照顧，且二名子女自出生後健保費用均由相對人支付迄\n    今，就醫無虞。然聲請人竟於二名子女回到○○後約三個月\n    ，以相對人行蹤成謎，有三、四年從未探視子女等不實之情\n    ，提起本件聲請。\n、聲請人現已另有同居女友，且亦育有二名未成年子女，依聲\n    請人目前之收入及生活狀況，實難以同時扶養四名子女；而\n    相對人目前任職於○○○○股份有限公司擔任行政人員，另\n    有存款1086萬3303元，與祖父○○同住，相對人之父○○經\n    營事業有成、資力豐厚，亦全力支援相對人日後對二名子女\n    之照顧，相對人有充分之家庭支援系統，亦可提供良好之生\n    活環境，足以負擔對二名子女之扶養義務，另二名子女均為\n    學齡前之女童，由同性別之相對人照顧，自較符合子女之利\n    益。\n、依鈞院委託○○○○○○○○○○○○○○○○基金會及○\n    ○○○○○社會福利關懷協會之所製作之訪視報告，兩名未\n    成年子女目前雖與聲請人同住，然：\n    、就居住狀況方面，聲請人目前居住房屋為聲請人同居人\n    母親所有，為公寓式住宅，提供聲請人與其同居人共同居住\n    ，而兩名被監護人同一寢室，則二名未成年子女目前所居住\n    之房屋，並非聲請人或其親人所有，是否可穩定長期居住，\n    似仍繫於不確定狀態；、就支持系統部份，聲請人似無親\n    友手足可協助就近提供照顧兩名子女，端料聲請人個人之力\n    量，反觀相對人父親、兄長皆可協助照顧兩未成年人，家中\n    外籍看護及管家在暑假期間都曾協助照顧未成年人，另相對\n    人之親友皆居住附近，均可協助照料，足認相對人在支持系\n    統上顯然較聲請人為佳；、就經濟方面，聲請人曾於○○\n    外包廠商從事○○○○工作約兩年多時間，月薪約4萬6,000\n    元，且須輪三班，目前則於住家鄰近車床工程工廠上班半年\n    左右，底薪有2萬2,500元，然每日加班至12小時，每月可達\n    4萬元，但因扶養四名子女，故每月生活費支出較高；而相\n    對人有固定之工作及收入，與父親同住，省去一切開銷，在\n    生活上並不虞匱乏，在經濟狀況方面穩定，家族又為○○○\n    ○○○主要股東，經濟狀況良好，且名下尚有存款一千餘萬\n    元及股票多筆，足認相對人顯然較能提供兩名子女穩定優裕\n    之生活；、就親職方面，聲請人表示曾因窮困潦倒而至醫\n    院計畫賣器官換取金錢，幸獲醫院社工開導和給予協助，並\n    提供相關社福資源，聲請人遂而得以維持生活，聲請人與目\n    前同居人乃多年鄰居朋友，與其同居後亦會協助照顧兩名被\n    監護人，然聲請人每日工作時間頗長，應多賴其同居人照顧\n    相對人所生之二名子女，然聲請人與同居人亦生育二名子女\n    ，且並無結婚之計劃，兩造所生二名子女雖亦稱聲請人之同\n    居人為媽咪，但彼此間並無任何血緣上或法律上之關係，此\n    種照顧子女之現況，如何維持長久？、就子女意願部份，\n    依社工之描述，二名子女之心智年齡尚無法理解監護意涵，\n    無法針對監護歸屬表達意願。雖二名子女在鈞院○○年○○\n    月○○日之調查程序時，曾表示想和聲請人同住，但考量二\n    名子女為○○、○○年出生6、7歲之幼童，尚無正確判斷事\n    理之能力，而兩造間在居住狀況、經濟條件各方面，差距頗\n    大，對於二名子女日後之成長所生影響至為重大，雖二名子\n    女目前已習慣與聲請人同住，但考量聲請人各方面可提供照\n    顧子女之條件，均存在十分不確定性，且聲請人一旦遭遇困\n    境，似無可供援手之人，二名子女果由聲請人為權利義務之\n    行使，並共同生活，似存在極多變數，均可能不利於子女，\n    從而，基於未成年人利益之考量，似應由相對人為權利義務\n    之行使，較符合子女之利益。\n、相對人於聲請人提出本件改定監護權事件前，認二名未成年\n    子女既為兩造共同生育，縱彼此無婚姻關係，仍可同時負擔\n    子女權利義務之行使，故過去並未就單獨行使監護權為任何\n    主張，然聲請人既以相對人不知去向、未盡監護責任為由，\n    主張由其單獨行使監護權云云，則相對人考量未成年子女之\n    未來成長，基於上述之理由，認客觀之狀況，應由相對人為\n    權利義務之行使較符合子女之利益，而聲請人為二名子女之\n    父親，苟監護權可由相對人行使，相對人亦同意聲請人可充\n    份探視子女，以利二名子女可同時在父親、母親之關愛下成\n    長。\n、並聲明：、兩造所生未成年子女甲○○、乙○○之權利義\n    務改由相對人行使；、聲請費用由聲請人負擔。\n三、按行使、負擔權利義務之一方未盡保護教養之義務或對未成\n    年子女有不利之情事者，他方、未成年子女、主管機關、社\n    會福利機構或其他利害關係人得為子女之利益，請求法院改\n    定之，民法第1055條第3項定有明文。又民法第1055條之1復\n    規定，法院決定未成年子女權利義務之行使或負擔時，應以\n    未成年子女之利益為原則，尤應注意：一、子女之年齡、性\n    別、人數及健康情形，二、子女之意願及人格發展之需要，\n    三、父母之年齡、職業、品行、健康情形、經濟能力及生活\n    狀況，四、父母保護教養子女之意願及態度，五、父母子女\n    間或未成年子女與其他共同生活之人間之感情狀況。\n四、經查：\n、聲請人主張兩造未婚同居，育有未成年長女甲○○（民國00\n    年0月00日出生）、次女乙○○（民國00年0月0日出生），\n    聲請人分別於○○年○○月○○日及○○年○○月○○日認\n    領，就二名未成年子女監護權協議由兩造共同行使，兩造於\n    97年間協議分手，目前二名未成年子女與聲請人同住等情，\n    有戶籍謄本影本2份附卷可稽，並為相對人到庭所不爭執，\n    堪信為真實。\n、聲請人主張相對人因另有交往對象，而與聲請人協議分手，\n    分手後相對人將二名子女交由聲請人養育即行蹤成迷，迄今\n    約有3至4年未前來探視女兒或以電話關心女兒云云；為相對\n    人所否認，並以前詞置辯。查聲請人於本院調查時坦承：與\n    現在同居人○○是在相對人父親告我妨害家庭案件時開始交\n    往，那時約○○年左右，三人曾同居在一起，我那時跟聲請\n    人表示，如果不同意我○○同居可以離開等語（見本院卷第\n    106頁）；又兩造長女甲○○於本院99年12月15日調查時證\n    稱：上個月在曾祖父家有看到相對人，聲請人每次帶我回○\n    ○曾祖父家時相對人都在，我曾與兩造同住，為何分開我不\n    知道，是聲請人說要分開住就把我帶走等語（見本院卷第67\n    .頁）；兩造次女乙○○則證稱：我有與相對人同住過，後\n    來因為聲請人有時生氣，就把我們帶走，聲請人有時會開車\n    載我回○○找曾祖父，相對人都會在○○，相對人有時還會\n    來○○找我等語（見本院卷第70、71頁）。又兩造子女之健\n    保多年來由相對人負責支付乙節，有相對人提出之健保資料\n    可參（見本院卷第54頁）。顯然並非相對人棄兩造子女於不\n    顧擅自離家，而是兩造因感情破裂、聲請人另結新歡導致兩\n    造未繼續同居，兩造分居後聲請人雖與子女同住，但此段期\n    間相對人並非對子女毫無聞問，或下落不明，子女返回相對\n    人○○住處時多可見到相對人，且相對人更與本案審理中一\n    再表明希望取得子女監護權之意願，可見相對人並無聲請人\n    所述，置子女於不顧之情形。\n、證人即長女甲○○到庭證稱：我現與聲請人同住，我不會想\n    與相對人同住，希望以後與聲請人同住，因為聲請人一直愛\n    我，聲請人的同居人即○○媽媽對我好，但尚未與聲請人結\n    婚，現在是她在照顧我等語；而證人即次女乙○○亦到庭證\n    稱：聲請人與相對人二個我都喜歡，我現在與聲請人同住，\n    我不會想要與相對人同住，且我現在讀大班，希望可以跟聲\n    請人住，我要住在○○國小幼稚園那邊，現在我們家裡也有\n    ○○媽媽，新媽媽對我很好等語（見本院卷第69-71頁）。\n    查兩造所生未成年長女甲○○為○○年○○月○○日生，現\n    年○○歲，次女乙○○為○○年○○月○○日生，現年○○\n    足歲，固然無法完全理解監護之含意，但依證人到庭表達之\n    意願可知，其等習慣目前生活，喜歡聲請人與聲請人之同居\n    人○○，不願改變現在生活環境。\n、復經本院囑託○○市政府委託之○○○○○○○○○○○○\n    ○○○○○○○○基金會、○○市政府委託○○○○○○○\n    ○○○關懷協會，分別就兩造所生未成年子女權利義務之行\n    使負擔由何人任之為宜，為訪視調查報告。財團法人○○○\n    ○○○○○○○基金會於訪視聲請人及2名未成年子女後以\n    ○○年○○月○○日（○○）財○○字第○○○○號函附監\n    護權案件訪視調查報告書略以：「聲請人表示與相對人協議\n    分手後，兩名被監護人均由其獨立撫養、照顧，聲請人目前\n    有固定工作與收入，因扶養人口多、開銷較大，故經濟壓力\n    沈重，聲請人目前同居人會協助照顧兩名被監護人，兩名被\n    監護人亦稱呼聲請人同居人為媽咪，互動良好，已有一定情\n    感，兩名被監護人年齡尚幼，心智尚無法理解監護意涵，長\n    女表示偶會思念相對人，也喜歡至相對人○○住處與相對人\n    父親、祖父互動相處，然亦喜歡與聲請人和聲請人同居人共\n    同居住，不希望有遷移，建議因被監護人們已習慣目前生活\n    環境與照顧者，然有思念相對人的情緒，而相對人未居本會\n    管轄區域，本會無法調查相對人監護意願和親職能力，故若\n    無法證明變更目前居住環境對被監護人們成長較為有利，則\n    不適宜任意變更，建請法官基於兒童最佳利益為考量，酌審\n    子女親權歸屬，並維護未行使監護之一方正常行使探視權之\n    權益。」等語。又○○○○○○○○○○○○關懷協會則於\n    訪視相對人後以○○年○○月○○日○○○○（○○）字第\n    ○○○○○○○○號函附○○○○年度兒童少年監護權歸屬\n    調查工作訪視報告表略以：「相對人父親、兄長皆可協助照\n    顧兩未成年人，家中外籍看護及管家在暑假期間都曾協助照\n    顧未成年人，支持系統佳，…相對人有固定之工作及收入，\n    又與父親同住，省去一切開銷，在生活上並不虞匱乏，在經\n    濟狀況方面穩定，家族又為○○○○○○○○主要股東，經\n    濟狀況良好，聲請人因不在轄區內，故不知其經濟狀況，自\n    兩未成年人出生迄相對人離家，都是由兩造共同照顧，兩造\n    分手後，兩未成年人也陸陸續續返回相對人家中，與相對人\n    共同生活，且今年暑假居住一個月母女相聚，親子關係從未\n    減少。…請鈞院參酌另一方訪視結果及其他相關資料，為未\n    成年人福利做最佳之裁決。」等語。顯然聲請人雖經濟能力\n    不如相對人，但目前仍可提供未成年子女正常之居住成長環\n    境，且聲請人之同居人與未成年人互動良好，未成年人已習\n    慣目前生活，如驟然變動目前生活環境，難認對未成年人有\n    何特別之利益；相對人則經濟條件富裕，親屬支援系統良好\n    ，可給予未成年人經濟無虞之成長環境。\n、綜觀上開兩造所陳、訪視報告及未成年人甲○○、乙○○陳\n    述之意見，可知未成年人近年來由聲請人及其同居人共同扶\n    養照顧並住在一起，其等感情親密，未成年人更已稱呼相對\n    人同居人為「媽咪」，然依聲請人提出之戶籍謄本所示，聲\n    請人目前除與相對人共同生育之2名未成年子女外，另與同\n    居人○○育有2名子女，分別為○○與○○，聲請人與同居\n    人迄今仍未辦理結婚，但多年來同住一處，聲請人之家庭、\n    感情狀況不可謂不複雜，聲請人日後是否仍可提供未成年子\n    女一個完整的家庭？不得不令人憂心。又聲請人表示目前從\n    事○○工作，加上加班費每月收入43,000元左右，聲請人必\n    須負擔一家6口之生活，經濟壓力必然沈重。反觀，相對人\n    之原生家庭雖經濟富裕、相對人目前感情狀況較聲請人單純\n    ，但相較於聲請人而言，相對人與未成年子女之感情較為疏\n    離，未成年子女也均表達希望不要改變現況之意願，又相對\n    人情緒不穩定，於本院開庭時多次失控痛哭、大聲指責聲請\n    人、復因無法控制情緒而離開法庭，就教養子女而言，實為\n    不當之示範。相對人之外在客觀條件雖優越，但就相對人自\n    身之成熟穩定度以觀，若無家人在旁協助支持，難以想像如\n    何擔任母親此一角色。故本院比較兩造在親子關係、親職能\n    力、支持系統及環境關係等方面後，認實各有優劣，並無由\n    特定一方監護將較有利於未成年人之情形。\n、聲請人主張之改定監護理由，不可採信，已如前述。兩造原\n    約定未成年子女共同監護，本院審酌兩造對於子女之成長，\n    各有不可替代之功能，未成年子女已習慣與聲請人、其同居\n    人、同居人所生2名弟弟共同居住之現況，不願改變現有生\n    活環境，與聲請人之依附關係較相對人為深，但聲請人之感\n    情、家庭狀況亦非穩定，反觀相對人之經濟條件優渥，有良\n    好的親屬支持系統，且考量若改變親權歸屬對兩造、未成年\n    子女在心理上所造成之影響，並兼顧父母必要時可互相支援\n    協助，此外現階段並無明顯證據顯示若由兩造採共同任親權\n    監護之方式有何不利於2名子女之情事，故本院認現階段仍\n    宜由兩造共同行使負擔未成年子女之權利義務。\n、惟斟酌兩造實際分居兩地，因兩造對親權行使方式仍有歧見\n    ，無法協議決定未成年子女與何人同住，客觀上實行恐有所\n    困難，將不利於子女之身心發展，衡諸聲請人目前為2名子\n    女之生活主要照顧者，於生活及情感上均能滿足2名子女之\n    需要，其間互動關係緊密自然，為維護未成年人在穩定良好\n    環境中成長，認未成年子女由聲請人照顧同住，而賦予相對\n    人探視權，較符合2名子女之最佳利益。惟待2名未成年子女\n    就讀國中時，應尊重其等之意願，由其等自行選擇繼續與相\n    對人同住○○或至○○就學與聲請人同住，使未成年子女不\n    僅不需驟然面對環境改變，喪失目前感情依附之狀況，又可\n    利用此段時間充分與相對人及其家人培養感情，並於未成年\n    人較為年長後給予選擇之機會，期待相對人良好之經濟條件\n    可以提供未成年子女更開闊之教育選擇、成長環境，以維護\n    未成年子女之最佳利益。\n五、又按，會面交往乃基於親子關係所衍生之自然權利，因其不\n    僅為父母之權利，更為未成年子女之權利，亦應以子女之最\n    佳利益為考量。本院審酌兩造之情況，雖認兩造所生子女甲\n    ○○、乙○○權利義務之行使負擔由兩造共同任之，並由聲\n    請人照顧同住，然相對人與甲○○、乙○○親情之聯絡亦不\n    可加以剝奪，為免未成年人由聲請人照顧同住後導致其對相\n    對人感到陌生，甚至排斥，有剝奪相對人母愛之虞，兼顧子\n    女人格之正常發展及滿足親子孺慕之情，爰審酌甲○○、乙\n    ○○之年齡、生活狀況等情，酌定相對人與甲○○、乙○○\n    會面交往之方式與時間如附表所示。\n六、末按，父母對於未成年之子女，有保護及教養之權利義務；\n    又負扶養義務者有數人，而其親等同一時，應各依其經濟能\n    力，分擔義務，民法第1084條、第1115條第3項分別定有明\n    文；另法院依民法第1055條之規定，為酌定、改定或變更時\n    ，得命未行使或負擔權利義務之一方給付扶養費。前項扶養\n    費之給付，法院得依聲請或依職權，命為一次或分期給付。\n    分期給付遲誤一期履行者，其後之期間視為亦已到期，復為\n    非訟事件法第127條第1項、第2項所明定。經查：\n、本件兩造所生未成年長女甲○○、次女乙○○權利義務之行\n    使及負擔，雖由兩造共同任之，但與聲請人同住，故聲請人\n    為實際上需支出扶養費用之人，為使子女能受到較好之生活\n    照顧，本院參以兩造所生未成年長女甲○○、次女乙○○各\n    為○○年○○月○○日及○○年○○月○○日生，而聲請人\n    從事○○工作，底薪24,000元，含加班費後收入約43,000元\n    ，名下無不動產；相對人則表示目前任職○○股份有限公司\n    、名下有1千萬餘元之存款，此外尚有○○股份有限公司價\n    值300餘萬元之投資等經濟狀況，已據兩造陳述在卷，並有\n    服務證明書、結存餘額證明書在卷可參，復經本院依職權自\n    稅務電子閘門查詢兩造財產所得調件明細表附卷可憑。聲請\n    人請求相對人負擔子女之扶養費用，依兩造前揭收入與行政\n    院主計處公佈之「台灣地區家庭收支調查報告」平均每人每\n    月消費支出（按區域別分）之記載標準，兩造未成年長女甲\n    ○○、次女乙○○為學齡兒童，需人教育、照顧，並有食衣\n    住行育樂等基本之生活需要，並居住○○市境，而○○市98\n    年度平均每人每月之消費支出為16,126元，此有○○市98年\n    度家庭收支調查報告可參，而上述支出包括消費性支出及非\n    消費性支出，其項目已經包括食衣住行育樂等生活範圍，並\n    且有居住區域之劃分，應該是目前較能正確反映國民生活水\n    準之數據，且上開消費金額之計算，因係以消費為導向，較\n    符合一般扶養實情，而足採為計算之依據。且參以兩造所生\n    未成年子女就學、註冊繳費等所費不貲，況觀諸現今物價指\n    數高漲，未成年人每天所須花費之餐費、交通費、衣著費、\n    補習費用及其他基本娛樂支出等亦不在少數，上述計算標準\n    應較綜合所得稅之扶養親屬寬減額顯屬可採，復考量兩造之\n    收入、經濟能力等因素，本院認聲請人主張相對人應按月負\n    擔子女扶養費用每人每月各7,500元等情，尚屬適當且已偏\n    低，應予准許。\n、另按扶養費乃維持受扶養權利人生活所需之費用，其費用之\n    需求係陸續發生，而在行使負擔子女權利義務之一方，其支\n    出亦屬繼續性之給付，並非一次給付。又因按月支付之金額\n    非鉅，為恐相對人日後拒絕或拖延，聲請人勢必多次奔波勞\n    累聲請強制執行，恐有害及子女利益，且父母子女血緣至親\n    ，父母對於子女之親情、撫育同等重要，對於子女人格形成\n    之過程均扮演重要角色，為滿足父女親情以享天倫，暨相對\n    人與子女間得藉由按月支付扶養費用過程，增進親情之交流\n    。從而，爰依聲請人之請求，認相對人應於聲請人與未成年\n    子女同住期間，負擔長女甲○○、次女乙○○之扶養費用每\n    人每月7,500元，並自本裁定確定之日起，按月於每月10日\n    起交付予聲請人代為管理支用，如相對人遲誤一期履行者，\n    其後之期間視為亦已到期。\n七、綜上所述，聲請人聲請改定兩造未成年子女權利義務行使或\n    負擔由聲請人任之，為無理由，應予駁回。又本院認從未成\n    年子女之最佳利益考量，對於甲○○、乙○○權利義務行使\n    或負擔仍以由兩造共同任之為宜，並考量兩造分居兩地，維\n    護未成年子女在穩定環境中成長，依職權酌定未成年子女由\n    聲請人照顧同住，兩造並應於未成年子女就讀國中後尊重其\n    意願自行決定，並賦予相對人之探視權，酌定相對人與甲○\n    ○、乙○○會面交往方式及期間如附表所示，並依聲請人之\n    請求，酌定相對人應負擔未成年子女與聲請人同住期間之扶\n    養費。\n八、爰依非訟事件法第21條第1項，裁定如主文。\n中    華    民    國    100   年    4    月    29    日\n                     家事法庭法  官  <a href=\"https://www.pingluweb.com.tw/#!judgeDetail?id=50e3f66521129327c1d372b9\" target=\"_blank\">洪嘉蘭</a>\n以上正本係照原本作成。\n如不服本裁定應於送達後10日內向本院提出抗告狀，並繳納抗告\n費新臺幣1,000元。\n中    華    民    國    100   年    4    月    29    日\n                             書記官  許家瑜\n \n附表：\n相對人與長女甲○○、次女乙○○會面、交往之時間、方式及應\n遵守事項：\n壹、時間與方式：\n一、時間：\n、每月任擇二週之週五下午六時起至週日下午六時止。\n、在不妨礙學校課業與活動之情況，除仍得維持前述所示之會\n    面交往方式外，相對人每年寒假得增加7日，暑假期間，得增\n    加15日與長女甲○○、次女乙○○攜回同住之期間，增加之\n    日數，均可分割或連續為之。\n二、方式：相對人或其家人應於事前一日通知聲請人，確認到場\n    接回之時間，由相對人或其家人至聲請人住處接子女外出，\n    並得外宿於相對人住處或相對人指定之地點。相對人並應於\n    約定之時間，送子女返回聲請人住處。相對人或其家人到場\n    接子女的時間若有延擱，得延長半小時，逾時視同放棄當次\n    的會面交往。\n貳、除上述外，相對人得隨時探視或電話、書信聯絡子女，但上述\n    探視、聯絡不得影響子女之正常作息生活。\n參、子女之地址或聯絡方式或就讀學校如有變更，聲請人應隨時通\n    知相對人。\n肆、上述會面交往方式及時間，得經由相對人及聲請人之同意，予以\n    協調變更。\n伍、遵守事項：\n一、不得有危害子女身心健康之行為。\n二、在實施會面交往之日，相對人或其家人不得遲延交回子女，被\n    告不得遲延交付子女。\n三、兩造不得對子女灌輸反抗對造之觀念。\n四、如子女於會面交往中患病或有其他急迫情形應即通知聲請人，\n    若聲請人無法就近照料或處理時，相對人應為必要之醫療措施，\n    仍須善盡對子女保護教養之義務。\n陸、應注意事項：聲請人如無正當理由未遵守交付子女義務或違\n    反前開應行注意事項時，相對人得依民法第1055條第3項規\n    定，請求法院改由相對人行使負擔子女之權利義務；相對人\n    如無正當理由違反前開探視時應行注意事項或未準時交還子\n    女時，被告得依民法第1055條第5項、非訟事件法第127條第\n    1項之規定，禁止相對人繼續探視或減少探視之次數。\n","courtCode":"CYD","fulltext":null,"gist":null,"identifier":"CYDV,99,監,124,20110429,1-e0a4c44e-7aa0-4019-80c8-09825ac07a0c","issue":"改定監護人","jno":"124","jtype":"R","judgeDate":1304006400000,"jyear":99,"lastUpdate":1594305259206,"reportStatus":7,"source":"opendata","summary":null},"report":{"amount":0,"appellant":null,"appellantAgent":null,"appellantLawyer":null,"appellee":null,"appelleeAgent":null,"appelleeLawyer":null,"assignCounsel":null,"beJudgedPerson":null,"caseNum":["99,監,124"],"caseType":"V","chosenCounsel":null,"clerk":"許家瑜","codeNum":"監","courtCode":"CYD","defendant":null,"defendantAgent":null,"defendantLawyer":null,"flag":false,"identifier":"CYDV,99,監,124,20110429,1-e0a4c44e-7aa0-4019-80c8-09825ac07a0c","inmate":null,"interlocutoryPetitioner":null,"jno":"124","jtype":"R","judge":null,"judgeDate":1304006400000,"jyear":99,"lastUpdate":1594305259206,"lawyerCustomers":null,"level":1,"lose":null,"main":"聲請人關於改定監護之聲請駁回。\n兩造所生未成年子女甲○○（女、民國00年0月00日生）、次女\n乙○○（女、民國00年0月0日生）權利義務之行使或負擔，仍由\n兩造共同任之，並於就讀國中前由聲請人照顧同住，相對人得依\n附表所示之方式、時間與甲○○、乙○○會面交往。\n相對人應自本裁定確定之日起，分別至長女甲○○、次女乙○○\n成年之日止，於其等與聲請人同住期間，負擔長女甲○○、次女\n乙○○之扶養費用每人每月各新台幣柒仟伍佰元，並按月於每月\n十日前交付予聲請人代為管理支用，如相對人遲誤一期履行者，\n其後之期間視為亦已到期。\n聲請費用由聲請人負擔。","money":0,"petitioner":["丙○○"],"petitionerAgent":null,"petitionerLawyer":["○○○"],"plaintiff":null,"plaintiffAgent":null,"plaintiffLawyer":null,"presideJudge":"洪嘉蘭","previousCaseNum":null,"previousCourtCode":null,"previousJudgeDate":null,"privateProsecutor":null,"proportion":0.0,"prosecutor":null,"publicDefender":null,"publicJudge":null,"puisne":null,"respondent":null,"result":2,"sentence":null,"statute":["民法第1055條","民法第1055條第5項","民法第1084條","民法第1055條第3項","民法第1115條第3項","民法第1055條之1"],"tags":null,"type":"民事裁定","win":null},"statute":[{"items":[{"cnum":"第一千零五十五條","num":"第1055條","val":1055},{"cnum":"第一千零五十五條第五項","num":"第1055條第5項","val":1055},{"cnum":"第一千零五十五條第三項","num":"第1055條第3項","val":1055},{"cnum":"第一千零五十五條之一","num":"第1055條之1","val":1055},{"cnum":"第一千零八十四條","num":"第1084條","val":1084},{"cnum":"第一千一百十五條第三項","num":"第1115條第3項","val":1115}],"statute":"民法"}],"tags":null},"success":true}