{"lastError":"","response":{"reportBase":{"caseNum":"100,監,494","caseType":"V","codeNum":"監","content":"臺灣板橋地方法院民事裁定　　　　　　　100年度監字第494號\n聲　請　人　蕭志雄\n相　對　人\n即受監護宣\n告人　　　　蕭志宏\n監　護　人　蕭玉美\n關　係　人　丁秀珠\n上列當事人聲請改定監護人事件，本院裁定如下：\n    主    文\n改定蕭志雄（男，民國○○○年○月○日生，身分證統一編號：\nＺ000000000號）為受監護宣告之人蕭志宏之監護人。\n指定丁秀珠（女，民國○○○年○月○○○日生，身分證統一編\n號：Ｚ000000000號）為會同開具財產清冊之人。\n原監護人蕭玉美應將受監護宣告之人蕭志宏之財產移交予新監護\n人蕭志雄。\n聲請程序費用新臺幣壹仟元由聲請人負擔。\n    理    由\n一、本件聲請意旨略以：聲請人為相對人之胞弟，相對人因重度\n    智障，已不能為（受）意思表示或辨識其效果，經鈞院於民\n    國99年6 月21日以99年度監宣字第111 號裁定宣告為受監護\n    宣告之人，並選定關係人蕭玉美為監護人，及指定丁秀珠為\n    會同開具財產清冊之人。嗣後關係人蕭玉美因與現任男友論\n    及婚嫁，如繼續照顧相對人蕭志宏恐有不便之處，而與聲請\n    人商量後，雙方同意改由聲請人擔任相對人蕭志宏之監護人\n    ，亦不違反相對人之最佳利益，為此請求鈞院裁定改由聲請\n    人蕭志雄擔任相對人之監護人，指定丁秀珠為會同開具財產\n    清冊之人等語。\n二、按受監護宣告之人應置監護人；法院選定監護人時，應依受\n    監護宣告之人之最佳利益，優先考量受監護宣告之人之意見\n    ，審酌一切情狀，並注意下列事項：一、受監護宣告之人之\n    身心狀態與生活及財產狀況。二、受監護宣告之人與其配偶\n    、子女或其他共同生活之人間之情感狀況。三、監護人之職\n    業、經歷、意見及其與受監護宣告之人之利害關係。四、法\n    人為監護人時，其事業之種類與內容，法人及其代表人與受\n    監護宣告之人之利害關係，民法第1110條及第1111條之1 分\n    別定有明文。又有事實足認監護人不符受監護人之最佳利益\n    ，或有顯不適任之情事者，法院得依受監護人、四親等內之\n    親屬、檢察官、主管機關或其他利害關係人之聲請，改定適\n    當之監護人；法院依第1094條第3 項選定監護人或依第1106\n    條及第1106條之1 另行選定或改定監護人時，應同時指定會\n    同開具財產清冊之人，民法第1113條準用民法第1106條之1\n    及第1094條第4 項亦有明示。\n三、經查：聲請人主張之事實，業據提出戶籍謄本為證，並經關\n    係人蕭玉美到庭陳述：「我已經有男朋友，交往一年多，也\n    論及婚嫁，如果繼續照顧弟弟，男方會有意見，認為我有哥\n    哥，弟弟應該給哥哥監護。我也同意改由聲請人來監護。」\n    、「我父親在今年1 月過世，男方說對年就可以結婚。」等\n    語（參見本院100 年9 月5 日非訟事件筆錄），堪認聲請人\n    主張應信為真實。本院依上開調查結果，認關係人蕭玉美因\n    準備結婚，礙於夫家傳統觀念，對於親自處理相對人相關事\n    務恐有無力之處，其擔任相對人之監護人確有不符合相對人\n    最佳利益之情事，並審酌聲請人蕭志雄有監護相對人之意願\n    及能力，並適於任之，是由聲請人負責護養及照顧相對人並\n    管理其財產，應能符合相對人之最佳利益，爰改定聲請人蕭\n    志雄為相對人之監護人。另本院參酌關係人丁秀珠為相對人\n    之大嫂，爰依上揭規定，同時指定關係人丁秀珠為會同開具\n    財產清冊之人。\n四、又按監護人變更時，原監護人應即將受監護人之財產移交於\n    新監護人。受監護之原因消滅時，原監護人應即將受監護人\n    之財產交還於受監護人；如受監護人死亡時，交還於其繼承\n    人。前二項情形，原監護人應於監護關係終止時起二個月內\n    ，為受監護人財產之結算，作成結算書，送交新監護人、受\n    監護人或其繼承人。新監護人、受監護人或其繼承人對於前\n    項結算書未為承認前，原監護人不得免其責任。且按監護人\n    死亡時，前條移交及結算，由其繼承人為之；其無繼承人或\n    繼承人有無不明者，由新監護人逕行辦理結算，連同依第10\n    99條規定開具之財產清冊陳報法院。此分別為民法第1107條\n    及第1108條所明定。本件受監護宣告人蕭志宏既經本院分別\n    改定聲請人蕭志雄任監護人及指定丁秀珠為會同開具財產清\n    冊之人，則原監護人蕭玉美自應依上開規定，將受監護宣告\n    之人蕭志宏之財產移交予新監護人蕭志雄，爰裁定如主文所\n    示第3 項。\n五、依非訟事件法第21條第1項前段，裁定如主文。\n中    華    民    國    100   年    10    月    25    日\n                  家事法庭  法  官  <a href=\"https://www.pingluweb.com.tw/#!judgeDetail?id=50e3f65b21129327c1d36cfb\" target=\"_blank\">劉大衛</a>\n以上為正本係照原本作成\n如對本裁定抗告須於裁定送達後10日內向本院提出抗告狀，並繳\n納抗告費新臺幣1,000元。\n中    華    民    國    100   年    10    月    25    日\n                            書記官  郭雅妮\n","courtCode":"PCD","fulltext":null,"gist":null,"identifier":"PCDV,100,監,494,20111025,1-f904ebe4-07e5-4249-ac79-b453c9950982","issue":"改定監護人","jno":"494","jtype":"R","judgeDate":1319472000000,"jyear":100,"lastUpdate":1594311573856,"reportStatus":7,"source":"opendata","summary":null},"report":{"amount":0,"appellant":null,"appellantAgent":null,"appellantLawyer":null,"appellee":null,"appelleeAgent":null,"appelleeLawyer":null,"assignCounsel":null,"beJudgedPerson":null,"caseNum":["100,監,494"],"caseType":"V","chosenCounsel":null,"clerk":"郭雅妮","codeNum":"監","courtCode":"PCD","defendant":null,"defendantAgent":null,"defendantLawyer":null,"flag":false,"identifier":"PCDV,100,監,494,20111025,1-f904ebe4-07e5-4249-ac79-b453c9950982","inmate":null,"interlocutoryPetitioner":null,"jno":"494","jtype":"R","judge":null,"judgeDate":1319472000000,"jyear":100,"lastUpdate":1594311573855,"lawyerCustomers":null,"level":1,"lose":null,"main":"改定蕭志雄（男，民國○○○年○月○日生，身分證統一編號：\nＺ000000000號）為受監護宣告之人蕭志宏之監護人。\n指定丁秀珠（女，民國○○○年○月○○○日生，身分證統一編\n號：Ｚ000000000號）為會同開具財產清冊之人。\n原監護人蕭玉美應將受監護宣告之人蕭志宏之財產移交予新監護\n人蕭志雄。\n聲請程序費用新臺幣壹仟元由聲請人負擔。","money":0,"petitioner":["即受監護宣","丁秀珠","告人蕭志宏","蕭志雄","相對人"],"petitionerAgent":null,"petitionerLawyer":null,"plaintiff":null,"plaintiffAgent":null,"plaintiffLawyer":null,"presideJudge":"劉大衛","previousCaseNum":null,"previousCourtCode":null,"previousJudgeDate":null,"privateProsecutor":null,"proportion":0.0,"prosecutor":null,"publicDefender":null,"publicJudge":null,"puisne":null,"respondent":null,"result":0,"sentence":null,"statute":["民法第1111條之1","民法第1110條","民法第1113條","民法第1108條","民法第1106條之1","民法第1107條","民法第1094條第4項"],"tags":null,"type":"民事裁定","win":null},"statute":[{"items":[{"cnum":"第一千零九十四條第四項","num":"第1094條第4項","val":1094},{"cnum":"第一千一百零六條之一","num":"第1106條之1","val":1106},{"cnum":"第一千一百零七條","num":"第1107條","val":1107},{"cnum":"第一千一百零八條","num":"第1108條","val":1108},{"cnum":"第一千一百十條","num":"第1110條","val":1110},{"cnum":"第一千一百十一條之一","num":"第1111條之1","val":1111},{"cnum":"第一千一百十三條","num":"第1113條","val":1113}],"statute":"民法"}],"tags":null},"success":true}