{"lastError":"","response":{"reportBase":{"caseNum":"100,親,119","caseType":"V","codeNum":"親","content":"臺灣彰化地方法院民事裁定　　　　　　　100年度親字第119號\n原　　　告　許喬柔\n被　　　告　吳雅婷\n上列當事人間停止親權並改定監護人事件，本院裁定如下：\n    主  文\n本件移送臺灣屏東地方法院。\n    理  由\n一、按訴訟之全部或一部，法院認為無管轄權者，依原告聲請或\n    依職權以裁定移送於其管轄法院，民事訴訟法第28條第1項\n    定有明文。\n二、次按宣告停止親權或撤銷其宣告之訴，專屬行親權人或曾行\n    親權人住所地之法院管轄，亦為民事訴訟法第592條所明定\n    ，查本件被告吳雅婷即行親權人，其住所地為屏東，有戶籍\n    謄本附卷可參，依上開說明，應專屬子女住所地之法院即臺\n    灣屏東地方法院管轄，茲原告向無管轄權之本院起訴，顯係\n    違誤。\n三、爰裁定如主文。\n中    華    民    國   100    年    10    月    3     日\n                        臺灣彰化地方法院家事法庭\n                              法    官  <a href=\"https://www.pingluweb.com.tw/#!judgeDetail?id=50e3f66a21129327c1d375c7\" target=\"_blank\">謝仁棠</a>\n以上正本係照原本作成。\n如對本裁定抗告，須於裁定送達後10日之不變期間內，向本院提\n出抗告狀，並繳納抗告費新臺幣1,000元。\n中    華    民    國   100    年    10    月    3     日\n                              書 記 官  陳如玲\n","courtCode":"CHD","fulltext":null,"gist":null,"identifier":"CHDV,100,親,119,20111003,1-ff6e782f-0662-4f8e-ad1c-6ee7a852f39b","issue":"停止親權並改定監護人","jno":"119","jtype":"R","judgeDate":1317571200000,"jyear":100,"lastUpdate":1594311458625,"reportStatus":7,"source":"opendata","summary":null},"report":{"amount":0,"appellant":null,"appellantAgent":null,"appellantLawyer":null,"appellee":null,"appelleeAgent":null,"appelleeLawyer":null,"assignCounsel":null,"beJudgedPerson":null,"caseNum":["100,親,119"],"caseType":"V","chosenCounsel":null,"clerk":"陳如玲","codeNum":"親","courtCode":"CHD","defendant":["吳雅婷"],"defendantAgent":null,"defendantLawyer":null,"flag":false,"identifier":"CHDV,100,親,119,20111003,1-ff6e782f-0662-4f8e-ad1c-6ee7a852f39b","inmate":null,"interlocutoryPetitioner":null,"jno":"119","jtype":"R","judge":null,"judgeDate":1317571200000,"jyear":100,"lastUpdate":1594311458624,"lawyerCustomers":null,"level":1,"lose":null,"main":"本件移送臺灣屏東地方法院。","money":0,"petitioner":null,"petitionerAgent":null,"petitionerLawyer":null,"plaintiff":["許喬柔"],"plaintiffAgent":null,"plaintiffLawyer":null,"presideJudge":"謝仁棠","previousCaseNum":null,"previousCourtCode":null,"previousJudgeDate":null,"privateProsecutor":null,"proportion":0.0,"prosecutor":null,"publicDefender":null,"publicJudge":null,"puisne":null,"respondent":null,"result":0,"sentence":null,"statute":["民事訴訟法第592條","民事訴訟法第28條第1項"],"tags":null,"type":"民事裁定","win":null},"statute":[{"items":[{"cnum":"第二十八條第一項","num":"第28條第1項","val":28},{"cnum":"第五百九十二條","num":"第592條","val":592}],"statute":"民事訴訟法"}],"tags":null},"success":true}