{"lastError":"","response":{"reportBase":{"caseNum":"100,親,42","caseType":"V","codeNum":"親","content":"臺灣彰化地方法院民事裁定　100年度親字第42號\n原　　　告　陳再添\n訴訟代理人　陳清華\n被　　　告　陳旭旻\n被　　　告　柳淑芬\n上列當事人間請求停止親權並改定監護人事件本院裁定如下：\n    主  文\n原告之訴駁回。\n訴訟費用由原告負擔。\n    理  由\n一、按提起民事訴訟應依法繳納裁判費，此為必須具備之程式，\n    次按「非因財產權而起訴者，徵收裁判費新臺幣三千元」；\n    民事訴訟法第77條之14第1項定有明文。\n二、本件原告起訴請求停止親權並改定監護人事件，揆諸前揭法\n    條規定徵收裁判費新臺幣三千元，惟原告起訴僅繳納裁判費\n    新臺幣一千元，經本院於民國100年7月29日裁定命原告於裁\n    定送達5日內補正（補繳裁判費新臺幣二千元）。該項裁定\n    已於民國100年8月9日送達原告，有送達證書附卷可憑。\n三、原告逾期迄未補正，其訴顯難認為合法，應予駁回。（並經\n    本院於100年8月31日審理後當庭向原告訴訟代理人陳清華諭\n    知本件原告之訴駁回）。\n四、依民事訴訟法第249條第1項第6款、第95條、裁定如主文。\n中    華    民    國   100    年    8     月    31    日\n                  家事法庭    法  官  <a href=\"https://www.pingluweb.com.tw/#!judgeDetail?id=50e3f66021129327c1d36fb4\" target=\"_blank\">施坤樹</a>\n以上正本係照原本作成。\n如對本裁定抗告，須於裁定送達後10日內向本院提出抗告狀。\n中    華    民    國   100    年    8     月    31    日\n                              書記官  許珍滋\n","courtCode":"CHD","fulltext":null,"gist":null,"identifier":"CHDV,100,親,42,20110831,2-4f162af5-ca2b-40c4-ac02-d44890d049ee","issue":"停止親權並改定監護人","jno":"42","jtype":"R","judgeDate":1314720000000,"jyear":100,"lastUpdate":1594308786020,"reportStatus":7,"source":"opendata","summary":null},"report":{"amount":0,"appellant":null,"appellantAgent":null,"appellantLawyer":null,"appellee":null,"appelleeAgent":null,"appelleeLawyer":null,"assignCounsel":null,"beJudgedPerson":null,"caseNum":["100,親,42"],"caseType":"V","chosenCounsel":null,"clerk":"許珍滋","codeNum":"親","courtCode":"CHD","defendant":["陳旭旻","柳淑芬"],"defendantAgent":null,"defendantLawyer":null,"flag":false,"identifier":"CHDV,100,親,42,20110831,2-4f162af5-ca2b-40c4-ac02-d44890d049ee","inmate":null,"interlocutoryPetitioner":null,"jno":"42","jtype":"R","judge":null,"judgeDate":1314720000000,"jyear":100,"lastUpdate":1594308786019,"lawyerCustomers":null,"level":1,"lose":null,"main":"原告之訴駁回。\n訴訟費用由原告負擔。","money":0,"petitioner":null,"petitionerAgent":null,"petitionerLawyer":null,"plaintiff":["陳再添"],"plaintiffAgent":["陳清華"],"plaintiffLawyer":null,"presideJudge":"施坤樹","previousCaseNum":null,"previousCourtCode":null,"previousJudgeDate":null,"privateProsecutor":null,"proportion":0.0,"prosecutor":null,"publicDefender":null,"publicJudge":null,"puisne":null,"respondent":null,"result":2,"sentence":null,"statute":["民事訴訟法第77條之14第1項","民事訴訟法第95條","民事訴訟法第249條第1項第6款"],"tags":null,"type":"民事裁定","win":null},"statute":[{"items":[{"cnum":"第七十七條之十四第一項","num":"第77條之14第1項","val":77},{"cnum":"第九十五條","num":"第95條","val":95},{"cnum":"第二百四十九條第一項第六款","num":"第249條第1項第6款","val":249}],"statute":"民事訴訟法"}],"tags":null},"success":true}