{"lastError":"","response":{"reportBase":{"caseNum":"103,監宣,281","caseType":"V","codeNum":"監宣","content":"臺灣臺北地方法院民事裁定　　　　　　103年度監宣字第281號\n聲　請　人　林昌期　\n相　對　人　林隆照　\n關　係　人　林隆源　\n　　　　　　林昌興　\n　　　　　　張林錦蘭\n　　　　　　謝智潔律師\n上列當事人間關於改定監護人事件，本院裁定如下：\n    主  文\n選任謝智潔律師為受監護宣告之人林隆照之程序監理人。\n    理  由\n按無程序能力人與其法定代理人有利害衝突之虞者，法院得依職\n權選任程序監理人；又關於聲請監護宣告事件，受監護宣告之人\n如無意思能力者，法院應依職權為其選任程序監理人，家事事件\n法第15條第1 項第1 款、第165 條分別定有明文。本件相對人林\n隆照為受監護宣告人，經本院調取98年度監字第97號卷宗核閱明\n確，揆諸前開規定，自有為其選任程序監理人之必要，爰選任謝\n智潔律師為其之程序監理人。裁定如主文。\n中    華    民    國   103    年    9     月    15    日\n               家事法庭  法      官  <a href=\"https://www.pingluweb.com.tw/#!judgeDetail?id=50e3f66921129327c1d3753c\" target=\"_blank\">藍家偉</a>\n以上正本係照原本作成。\n本裁定不得抗告。\n中    華    民    國   103    年    9     月    15    日\n                         書  記  官  蔡沛圻\n","courtCode":"TPD","fulltext":null,"gist":null,"identifier":"TPDV,103,監宣,281,20140915,2-8652dcbc-b0c0-44cc-9d94-d47129a04b9d","issue":"改定監護人","jno":"281","jtype":"R","judgeDate":1410710400000,"jyear":103,"lastUpdate":1594349190645,"reportStatus":7,"source":"opendata","summary":null},"report":{"amount":0,"appellant":null,"appellantAgent":null,"appellantLawyer":null,"appellee":null,"appelleeAgent":null,"appelleeLawyer":null,"assignCounsel":null,"beJudgedPerson":null,"caseNum":["103,監宣,281"],"caseType":"V","chosenCounsel":null,"clerk":"蔡沛圻","codeNum":"監宣","courtCode":"TPD","defendant":null,"defendantAgent":null,"defendantLawyer":null,"flag":false,"identifier":"TPDV,103,監宣,281,20140915,2-8652dcbc-b0c0-44cc-9d94-d47129a04b9d","inmate":null,"interlocutoryPetitioner":null,"jno":"281","jtype":"R","judge":null,"judgeDate":1410710400000,"jyear":103,"lastUpdate":1594349190645,"lawyerCustomers":null,"level":1,"lose":null,"main":"選任謝智潔律師為受監護宣告之人林隆照之程序監理人。","money":0,"petitioner":["林昌興","林隆源","張林錦蘭","謝智潔律師","林昌期"],"petitionerAgent":null,"petitionerLawyer":null,"plaintiff":null,"plaintiffAgent":null,"plaintiffLawyer":null,"presideJudge":"藍家偉","previousCaseNum":null,"previousCourtCode":null,"previousJudgeDate":null,"privateProsecutor":null,"proportion":0.0,"prosecutor":null,"publicDefender":null,"publicJudge":null,"puisne":null,"respondent":null,"result":0,"sentence":null,"statute":[],"tags":null,"type":"民事裁定","win":null},"statute":[],"tags":null},"success":true}