{"lastError":"","response":{"reportBase":{"caseNum":"103,家親聲,5","caseType":"V","codeNum":"家親聲","content":"臺灣基隆地方法院民事裁定　　　　　　103年度家親聲字第5號\n聲　請　人　王淑美\n上列聲請人與相對人蔡瀚鋒間改定監護人事件，本院裁定如下：\n    主  文\n聲請駁回。\n    理  由\n一、按因非財產權關係為聲請者，徵收費用新臺幣一千元，非訟\n    事件法第 14條第1項定有明文。而此費用，關係人未預納者\n    ，法院應限期命其預納；逾期仍不預納者，應駁回其聲請或\n    抗告，同法第 26條第1項復有明定。上述規定，於家事非訟\n    事件準用之，此觀之家事事件法第97條規定即明。\n二、本件聲請人聲請改定監護人事件，未據繳納聲請費，經本院\n    於民國103年1月6日以書面裁定命聲請人於收受裁定之日起5\n    日內補繳，該裁定業於103年1月16日依法寄存送達，有送達\n    證書在卷可稽，因聲請人並未領取，依家事事件法第97條準\n    用非訟事件法第31條再準用民事訴訟法第138條第1項規定，\n    自寄存之日起經10日發生效力，據以計算，係於同年1月26\n    日發生送達之效力。詎聲請人逾期迄未補正，有多元化案件\n    繳費狀況查詢清單、民事科查詢簡答表在卷可憑，其聲請顯\n    難認為合法，應予駁回。\n三、依家事事件法第97條、非訴事件法第26條第1項，裁定如主\n    文。\n中    華    民    國    103    年    2    月    7     日\n                  家事庭法  官  <a href=\"https://www.pingluweb.com.tw/#!judgeDetail?id=50e3f66621129327c1d37382\" target=\"_blank\">王美婷</a>\n以上正本係照原本作成。\n如不服本裁定應於送達後10日內向本院提出抗告狀，並繳納抗告\n費新臺幣1000元。\n中    華    民    國   103    年    2     月    7     日\n                        書記官  賴思穎\n","courtCode":"KLD","fulltext":null,"gist":null,"identifier":"KLDV,103,家親聲,5,20140207,2-941768e3-15cd-41c1-bf56-7c1584d2586e","issue":"改定監護人","jno":"5","jtype":"R","judgeDate":1391702400000,"jyear":103,"lastUpdate":1594296664966,"reportStatus":7,"source":"opendata","summary":null},"report":{"amount":0,"appellant":null,"appellantAgent":null,"appellantLawyer":null,"appellee":null,"appelleeAgent":null,"appelleeLawyer":null,"assignCounsel":null,"beJudgedPerson":null,"caseNum":["103,家親聲,5"],"caseType":"V","chosenCounsel":null,"clerk":"賴思穎","codeNum":"家親聲","courtCode":"KLD","defendant":null,"defendantAgent":null,"defendantLawyer":null,"flag":false,"identifier":"KLDV,103,家親聲,5,20140207,2-941768e3-15cd-41c1-bf56-7c1584d2586e","inmate":null,"interlocutoryPetitioner":null,"jno":"5","jtype":"R","judge":null,"judgeDate":1391702400000,"jyear":103,"lastUpdate":1594296664965,"lawyerCustomers":null,"level":1,"lose":null,"main":"聲請駁回。","money":0,"petitioner":["王淑美"],"petitionerAgent":null,"petitionerLawyer":null,"plaintiff":null,"plaintiffAgent":null,"plaintiffLawyer":null,"presideJudge":"王美婷","previousCaseNum":null,"previousCourtCode":null,"previousJudgeDate":null,"privateProsecutor":null,"proportion":0.0,"prosecutor":null,"publicDefender":null,"publicJudge":null,"puisne":null,"respondent":null,"result":2,"sentence":null,"statute":["民事訴訟法第138條第1項"],"tags":null,"type":"民事裁定","win":null},"statute":[{"items":[{"cnum":"第一百三十八條第一項","num":"第138條第1項","val":138}],"statute":"民事訴訟法"}],"tags":null},"success":true}