{"lastError":"","response":{"reportBase":{"caseNum":"100,親,51","caseType":"V","codeNum":"親","content":"臺灣彰化地方法院民事裁定　　　　　　　 100年度親字第51號\n原　　　告　高素綢\n被　　　告　張耀駿\n上列當事人間聲請停止親權並改定監護人事件，本院裁定如下：\n    主  文\n本件移送臺灣台中地方法院。\n    理  由\n一、按訴訟之全部或一部，法院認為無管轄權者，依原告聲請或\n    依職權以裁定移送於其管轄法院。民事訴訟法第28條第1項\n    定有明文。次按宣告停止親權或撤銷其宣告之訴，專屬行親\n    權人或曾行親權人住所地之法院管轄。民事訴訟法第592條\n    亦有明文。\n二、本件原告提起停止親權訴訟，經查被告張耀駿之住所地係在\n    台中市○區○○路141巷56之3號，有原告起訴狀可稽，依民\n    事訴訟法第592條規定，就有關被告張耀駿部分應由臺灣台\n    中地方法院管轄，茲原告就被告張耀駿部分向無管轄權之本\n    院起訴，顯係違誤。\n三、爰依職權將本件被告張耀駿部分移送該管轄法院。至於被告\n    陳姿佑部分，本院另行依法判決。\n四、爰裁定如主文。\n中    華    民    國   100    年    8     月    19    日\n                  家事法庭    法  官  <a href=\"https://www.pingluweb.com.tw/#!judgeDetail?id=50e3f66021129327c1d36fb4\" target=\"_blank\">施坤樹</a>\n正本係照原本作成。如對本裁定抗告，須於裁定送達後10日之不\n變期間內，向本院提出抗告狀。\n中    華    民    國   100    年    8     月    19    日\n                              書記官  許珍滋\n","courtCode":"CHD","fulltext":null,"gist":null,"identifier":"CHDV,100,親,51,20110819,2-ad047942-cea7-4344-8e94-71487df9089d","issue":"停止親權並改定監護人","jno":"51","jtype":"R","judgeDate":1313683200000,"jyear":100,"lastUpdate":1594308807671,"reportStatus":7,"source":"opendata","summary":null},"report":{"amount":0,"appellant":null,"appellantAgent":null,"appellantLawyer":null,"appellee":null,"appelleeAgent":null,"appelleeLawyer":null,"assignCounsel":null,"beJudgedPerson":null,"caseNum":["100,親,51"],"caseType":"V","chosenCounsel":null,"clerk":"許珍滋","codeNum":"親","courtCode":"CHD","defendant":["張耀駿"],"defendantAgent":null,"defendantLawyer":null,"flag":false,"identifier":"CHDV,100,親,51,20110819,2-ad047942-cea7-4344-8e94-71487df9089d","inmate":null,"interlocutoryPetitioner":null,"jno":"51","jtype":"R","judge":null,"judgeDate":1313683200000,"jyear":100,"lastUpdate":1594308807670,"lawyerCustomers":null,"level":1,"lose":null,"main":"本件移送臺灣台中地方法院。","money":0,"petitioner":null,"petitionerAgent":null,"petitionerLawyer":null,"plaintiff":["高素綢"],"plaintiffAgent":null,"plaintiffLawyer":null,"presideJudge":"施坤樹","previousCaseNum":null,"previousCourtCode":null,"previousJudgeDate":null,"privateProsecutor":null,"proportion":0.0,"prosecutor":null,"publicDefender":null,"publicJudge":null,"puisne":null,"respondent":null,"result":0,"sentence":null,"statute":["民事訴訟法第592條","民事訴訟法第28條第1項"],"tags":null,"type":"民事裁定","win":null},"statute":[{"items":[{"cnum":"第二十八條第一項","num":"第28條第1項","val":28},{"cnum":"第五百九十二條","num":"第592條","val":592}],"statute":"民事訴訟法"}],"tags":null},"success":true}