{"lastError":"","response":{"reportBase":{"caseNum":"102,監宣,415","caseType":"V","codeNum":"監宣","content":"臺灣臺南地方法院民事裁定　　　　　　102年度監宣字第415號\n聲　請　人　國軍退除役官兵輔導委員會臺南市榮民服務處\n法定代理人　朱維忠\n上列聲請人聲請改定受監護宣告人監護人事件，本院於民國103\n年1月20日所為之裁定，應更正如下：\n    主      文\n原裁定原本及正本中當事人欄、主文欄、理由欄關於「行政院國\n軍退除役官兵輔導委員會臺南市榮民服務處」之記載，應更正為\n「國軍退除役官兵輔導委員會臺南市榮民服務處」。\n    理      由\n一、按判決如有誤寫、誤算或其他類此之顯然錯誤者，法院得依\n    聲請或依職權以裁定更正，民事訴訟法第232條第1項定有明\n    文。此於非訟事件裁定亦準用之，非訟事件法第36條第3項\n    亦定有明文。\n二、查本院前開之裁定原本及正本有如主文所示之顯然錯誤，應\n    予更正。\n三、依首開規定裁定如主文。\n中    華    民    國   103    年    2     月    18    日\n                  家事法庭    法  官  <a href=\"https://www.pingluweb.com.tw/#!judgeDetail?id=50e3f66821129327c1d37489\" target=\"_blank\">葉惠玲</a>\n以上正本係照原本作成。\n如對本裁定抗告，須於裁定送達後10日內向本院提出抗告狀。\n中    華    民    國   103    年    2     月    18    日\n                              書記官  謝麗首\n","courtCode":"TND","fulltext":null,"gist":null,"identifier":"TNDV,102,監宣,415,20140218,3-6f6cba74-9280-48fe-8745-5e24f4ebf9c4","issue":"改定受監護宣告人監護人","jno":"415","jtype":"R","judgeDate":1392652800000,"jyear":102,"lastUpdate":1594296373928,"reportStatus":7,"source":"opendata","summary":null},"report":{"amount":0,"appellant":null,"appellantAgent":null,"appellantLawyer":null,"appellee":null,"appelleeAgent":null,"appelleeLawyer":null,"assignCounsel":null,"beJudgedPerson":null,"caseNum":["102,監宣,415"],"caseType":"V","chosenCounsel":null,"clerk":"謝麗首","codeNum":"監宣","courtCode":"TND","defendant":null,"defendantAgent":null,"defendantLawyer":null,"flag":false,"identifier":"TNDV,102,監宣,415,20140218,3-6f6cba74-9280-48fe-8745-5e24f4ebf9c4","inmate":null,"interlocutoryPetitioner":null,"jno":"415","jtype":"R","judge":null,"judgeDate":1392652800000,"jyear":102,"lastUpdate":1594296373927,"lawyerCustomers":null,"level":1,"lose":null,"main":"原裁定原本及正本中當事人欄、主文欄、理由欄關於「行政院國\n軍退除役官兵輔導委員會臺南市榮民服務處」之記載，應更正為\n「國軍退除役官兵輔導委員會臺南市榮民服務處」。","money":0,"petitioner":["國軍退除役官兵輔導委員會臺南市榮民服務處"],"petitionerAgent":null,"petitionerLawyer":null,"plaintiff":null,"plaintiffAgent":null,"plaintiffLawyer":null,"presideJudge":"葉惠玲","previousCaseNum":null,"previousCourtCode":null,"previousJudgeDate":null,"privateProsecutor":null,"proportion":0.0,"prosecutor":null,"publicDefender":null,"publicJudge":null,"puisne":null,"respondent":null,"result":0,"sentence":null,"statute":["民事訴訟法第232條第1項"],"tags":null,"type":"民事裁定","win":null},"statute":[{"items":[{"cnum":"第二百三十二條第一項","num":"第232條第1項","val":232}],"statute":"民事訴訟法"}],"tags":null},"success":true}